[{"name":"Abomasnow","type1":"Grass","hp":"90","attack":"92","defense":"75"},
{"name":"Abra","type1":"Psychic","hp":"25","attack":"20","defense":"15"},
{"name":"Absol","type1":"Dark","hp":"65","attack":"130","defense":"60"},
{"name":"Accelgor","type1":"Bug","hp":"80","attack":"70","defense":"40"},
{"name":"Aegislash Blade Forme","type1":"Steel","hp":"60","attack":"150","defense":"50"},
{"name":"Aegislash Shield Forme","type1":"Steel","hp":"60","attack":"50","defense":"150"},
{"name":"Aerodactyl","type1":"Rock","hp":"80","attack":"105","defense":"65"},
{"name":"Aggron","type1":"Steel","hp":"70","attack":"110","defense":"180"},
{"name":"Aipom","type1":"Normal","hp":"55","attack":"70","defense":"55"},
{"name":"Alakazam","type1":"Psychic","hp":"55","attack":"50","defense":"45"},
{"name":"Alcremie","type1":"Fairy","hp":"65","attack":"60","defense":"75"},
{"name":"Alolan Diglett","type1":"Ground","hp":"10","attack":"55","defense":"30"},
{"name":"Alolan Dugtrio","type1":"Ground","hp":"35","attack":"100","defense":"60"},
{"name":"Alolan Exeggutor","type1":"Grass","hp":"95","attack":"105","defense":"85"},
{"name":"Alolan Geodude","type1":"Rock","hp":"40","attack":"80","defense":"100"},
{"name":"Alolan Golem","type1":"Rock","hp":"80","attack":"120","defense":"130"},
{"name":"Alolan Graveler","type1":"Rock","hp":"55","attack":"95","defense":"115"},
{"name":"Alolan Grimer","type1":"Poison","hp":"80","attack":"80","defense":"50"},
{"name":"Alolan Marowak","type1":"Fire","hp":"60","attack":"80","defense":"110"},
{"name":"Alolan Meowth","type1":"Dark","hp":"40","attack":"35","defense":"35"},
{"name":"Alolan Muk","type1":"Poison","hp":"105","attack":"105","defense":"75"},
{"name":"Alolan Ninetales","type1":"Ice","hp":"73","attack":"67","defense":"75"},
{"name":"Alolan Persian","type1":"Dark","hp":"65","attack":"60","defense":"60"},
{"name":"Alolan Raichu","type1":"Electric","hp":"60","attack":"85","defense":"50"},
{"name":"Alolan Raticate","type1":"Dark","hp":"75","attack":"71","defense":"70"},
{"name":"Alolan Rattata","type1":"Dark","hp":"30","attack":"56","defense":"35"},
{"name":"Alolan Sandshrew","type1":"Ice","hp":"50","attack":"75","defense":"90"},
{"name":"Alolan Sandslash","type1":"Ice","hp":"75","attack":"100","defense":"120"},
{"name":"Alolan Vulpix","type1":"Ice","hp":"38","attack":"41","defense":"40"},
{"name":"Alomomola","type1":"Water","hp":"165","attack":"75","defense":"80"},
{"name":"Altaria","type1":"Dragon","hp":"75","attack":"70","defense":"90"},
{"name":"Amaura","type1":"Rock","hp":"77","attack":"59","defense":"50"},
{"name":"Ambipom","type1":"Normal","hp":"75","attack":"100","defense":"66"},
{"name":"Amoonguss","type1":"Grass","hp":"114","attack":"85","defense":"70"},
{"name":"Ampharos","type1":"Electric","hp":"90","attack":"75","defense":"85"},
{"name":"Anorith","type1":"Rock","hp":"45","attack":"95","defense":"50"},
{"name":"Appletun","type1":"Grass","hp":"110","attack":"85","defense":"80"},
{"name":"Applin","type1":"Grass","hp":"40","attack":"40","defense":"80"},
{"name":"Araquanid","type1":"Water","hp":"68","attack":"70","defense":"92"},
{"name":"Arbok","type1":"Poison","hp":"60","attack":"85","defense":"69"},
{"name":"Arcanine","type1":"Fire","hp":"90","attack":"110","defense":"80"},
{"name":"Arceus","type1":"Normal","hp":"120","attack":"120","defense":"120"},
{"name":"Archen","type1":"Rock","hp":"55","attack":"112","defense":"45"},
{"name":"Archeops","type1":"Rock","hp":"75","attack":"140","defense":"65"},
{"name":"Arctovish","type1":"Water","hp":"90","attack":"90","defense":"100"},
{"name":"Arctozolt","type1":"Electric","hp":"90","attack":"100","defense":"90"},
{"name":"Ariados","type1":"Bug","hp":"70","attack":"90","defense":"70"},
{"name":"Armaldo","type1":"Rock","hp":"75","attack":"125","defense":"100"},
{"name":"Aromatisse","type1":"Fairy","hp":"101","attack":"72","defense":"72"},
{"name":"Aron","type1":"Steel","hp":"50","attack":"70","defense":"100"},
{"name":"Arrokuda","type1":"Water","hp":"41","attack":"63","defense":"40"},
{"name":"Articuno","type1":"Ice","hp":"90","attack":"85","defense":"100"},
{"name":"Ash-Greninja","type1":"Water","hp":"72","attack":"145","defense":"67"},
{"name":"Audino","type1":"Normal","hp":"103","attack":"60","defense":"86"},
{"name":"Aurorus","type1":"Rock","hp":"123","attack":"77","defense":"72"},
{"name":"Avalugg","type1":"Ice","hp":"95","attack":"117","defense":"184"},
{"name":"Axew","type1":"Dragon","hp":"46","attack":"87","defense":"60"},
{"name":"Azelf","type1":"Psychic","hp":"75","attack":"125","defense":"70"},
{"name":"Azumarill","type1":"Water","hp":"100","attack":"50","defense":"80"},
{"name":"Azurill","type1":"Normal","hp":"50","attack":"20","defense":"40"},
{"name":"Bagon","type1":"Dragon","hp":"45","attack":"75","defense":"60"},
{"name":"Baltoy","type1":"Ground","hp":"40","attack":"40","defense":"55"},
{"name":"Banette","type1":"Ghost","hp":"64","attack":"115","defense":"65"},
{"name":"Barbaracle","type1":"Rock","hp":"72","attack":"105","defense":"115"},
{"name":"Barboach","type1":"Water","hp":"50","attack":"48","defense":"43"},
{"name":"Barraskewda","type1":"Water","hp":"61","attack":"123","defense":"60"},
{"name":"Basculin","type1":"Water","hp":"70","attack":"92","defense":"65"},
{"name":"Bastiodon","type1":"Rock","hp":"60","attack":"52","defense":"168"},
{"name":"Bayleef","type1":"Grass","hp":"60","attack":"62","defense":"80"},
{"name":"Beartic","type1":"Ice","hp":"95","attack":"110","defense":"80"},
{"name":"Beautifly","type1":"Bug","hp":"60","attack":"70","defense":"50"},
{"name":"Beedrill","type1":"Bug","hp":"65","attack":"90","defense":"40"},
{"name":"Beheeyem","type1":"Psychic","hp":"75","attack":"75","defense":"75"},
{"name":"Beldum","type1":"Steel","hp":"40","attack":"55","defense":"80"},
{"name":"Bellossom","type1":"Grass","hp":"75","attack":"80","defense":"95"},
{"name":"Bellsprout","type1":"Grass","hp":"50","attack":"75","defense":"35"},
{"name":"Bergmite","type1":"Ice","hp":"55","attack":"69","defense":"85"},
{"name":"Bewear","type1":"Normal","hp":"120","attack":"125","defense":"80"},
{"name":"Bibarel","type1":"Normal","hp":"79","attack":"85","defense":"60"},
{"name":"Bidoof","type1":"Normal","hp":"59","attack":"45","defense":"40"},
{"name":"Binacle","type1":"Rock","hp":"42","attack":"52","defense":"67"},
{"name":"Bisharp","type1":"Dark","hp":"65","attack":"125","defense":"100"},
{"name":"Blacephalon","type1":"Fire","hp":"53","attack":"127","defense":"53"},
{"name":"Black Kyurem","type1":"Dragon","hp":"125","attack":"170","defense":"100"},
{"name":"Blastoise","type1":"Water","hp":"79","attack":"83","defense":"100"},
{"name":"Blaziken","type1":"Fire","hp":"80","attack":"120","defense":"70"},
{"name":"Blipbug","type1":"Bug","hp":"25","attack":"20","defense":"20"},
{"name":"Blissey","type1":"Normal","hp":"255","attack":"10","defense":"10"},
{"name":"Blitzle","type1":"Electric","hp":"45","attack":"60","defense":"32"},
{"name":"Boldore","type1":"Rock","hp":"70","attack":"105","defense":"105"},
{"name":"Boltund","type1":"Electric","hp":"69","attack":"90","defense":"60"},
{"name":"Bonsly","type1":"Rock","hp":"50","attack":"80","defense":"95"},
{"name":"Bouffalant","type1":"Normal","hp":"95","attack":"110","defense":"95"},
{"name":"Bounsweet","type1":"Grass","hp":"42","attack":"30","defense":"38"},
{"name":"Braixen","type1":"Fire","hp":"59","attack":"59","defense":"58"},
{"name":"Braviary","type1":"Normal","hp":"100","attack":"123","defense":"75"},
{"name":"Breloom","type1":"Grass","hp":"60","attack":"130","defense":"80"},
{"name":"Brionne","type1":"Water","hp":"60","attack":"69","defense":"69"},
{"name":"Bronzong","type1":"Steel","hp":"67","attack":"89","defense":"116"},
{"name":"Bronzor","type1":"Steel","hp":"57","attack":"24","defense":"86"},
{"name":"Bruxish","type1":"Water","hp":"68","attack":"105","defense":"70"},
{"name":"Budew","type1":"Grass","hp":"40","attack":"30","defense":"35"},
{"name":"Buizel","type1":"Water","hp":"55","attack":"65","defense":"35"},
{"name":"Bulbasaur","type1":"Grass","hp":"45","attack":"49","defense":"49"},
{"name":"Buneary","type1":"Normal","hp":"55","attack":"66","defense":"44"},
{"name":"Bunnelby","type1":"Normal","hp":"38","attack":"36","defense":"38"},
{"name":"Burmy","type1":"Bug","hp":"40","attack":"29","defense":"45"},
{"name":"Butterfree","type1":"Bug","hp":"60","attack":"45","defense":"50"},
{"name":"Buzzwole","type1":"Bug","hp":"107","attack":"139","defense":"139"},
{"name":"Cacnea","type1":"Grass","hp":"50","attack":"85","defense":"40"},
{"name":"Cacturne","type1":"Grass","hp":"70","attack":"115","defense":"60"},
{"name":"Calyrex","type1":"Psychic","hp":"100","attack":"80","defense":"80"},
{"name":"Camerupt","type1":"Fire","hp":"70","attack":"100","defense":"70"},
{"name":"Carbink","type1":"Rock","hp":"50","attack":"50","defense":"150"},
{"name":"Carkol","type1":"Rock","hp":"80","attack":"60","defense":"90"},
{"name":"Carnivine","type1":"Grass","hp":"74","attack":"100","defense":"72"},
{"name":"Carracosta","type1":"Water","hp":"74","attack":"108","defense":"133"},
{"name":"Carvanha","type1":"Water","hp":"45","attack":"90","defense":"20"},
{"name":"Cascoon","type1":"Bug","hp":"50","attack":"35","defense":"55"},
{"name":"Castform","type1":"Normal","hp":"70","attack":"70","defense":"70"},
{"name":"Caterpie","type1":"Bug","hp":"45","attack":"30","defense":"35"},
{"name":"Celebi","type1":"Psychic","hp":"100","attack":"100","defense":"100"},
{"name":"Celesteela","type1":"Steel","hp":"97","attack":"101","defense":"103"},
{"name":"Centiskorch","type1":"Fire","hp":"100","attack":"115","defense":"65"},
{"name":"Chandelure","type1":"Ghost","hp":"60","attack":"55","defense":"90"},
{"name":"Chansey","type1":"Normal","hp":"250","attack":"5","defense":"5"},
{"name":"Charizard","type1":"Fire","hp":"78","attack":"84","defense":"78"},
{"name":"Charjabug","type1":"Bug","hp":"57","attack":"82","defense":"95"},
{"name":"Charmander","type1":"Fire","hp":"39","attack":"52","defense":"43"},
{"name":"Charmeleon","type1":"Fire","hp":"58","attack":"64","defense":"58"},
{"name":"Chatot","type1":"Normal","hp":"76","attack":"65","defense":"45"},
{"name":"Cherrim","type1":"Grass","hp":"70","attack":"60","defense":"70"},
{"name":"Cherubi","type1":"Grass","hp":"45","attack":"35","defense":"45"},
{"name":"Chesnaught","type1":"Grass","hp":"88","attack":"107","defense":"122"},
{"name":"Chespin","type1":"Grass","hp":"56","attack":"61","defense":"65"},
{"name":"Chewtle","type1":"Water","hp":"50","attack":"64","defense":"50"},
{"name":"Chikorita","type1":"Grass","hp":"45","attack":"49","defense":"65"},
{"name":"Chimchar","type1":"Fire","hp":"44","attack":"58","defense":"44"},
{"name":"Chimecho","type1":"Psychic","hp":"65","attack":"50","defense":"70"},
{"name":"Chinchou","type1":"Water","hp":"75","attack":"38","defense":"38"},
{"name":"Chingling","type1":"Psychic","hp":"45","attack":"30","defense":"50"},
{"name":"Cinccino","type1":"Normal","hp":"75","attack":"95","defense":"60"},
{"name":"Cinderace","type1":"Fire","hp":"80","attack":"116","defense":"75"},
{"name":"Clamperl","type1":"Water","hp":"35","attack":"64","defense":"85"},
{"name":"Clauncher","type1":"Water","hp":"50","attack":"53","defense":"62"},
{"name":"Clawitzer","type1":"Water","hp":"71","attack":"73","defense":"88"},
{"name":"Claydol","type1":"Ground","hp":"60","attack":"70","defense":"105"},
{"name":"Clefable","type1":"Fairy","hp":"95","attack":"70","defense":"73"},
{"name":"Clefairy","type1":"Fairy","hp":"70","attack":"45","defense":"48"},
{"name":"Cleffa","type1":"Fairy","hp":"50","attack":"25","defense":"28"},
{"name":"Clobbopus","type1":"Fighting","hp":"50","attack":"68","defense":"60"},
{"name":"Cloyster","type1":"Water","hp":"50","attack":"95","defense":"180"},
{"name":"Coalossal","type1":"Rock","hp":"110","attack":"80","defense":"120"},
{"name":"Cobalion","type1":"Steel","hp":"91","attack":"90","defense":"129"},
{"name":"Cofagrigus","type1":"Ghost","hp":"58","attack":"50","defense":"145"},
{"name":"Combee","type1":"Bug","hp":"30","attack":"30","defense":"42"},
{"name":"Combusken","type1":"Fire","hp":"60","attack":"85","defense":"60"},
{"name":"Comfey","type1":"Fairy","hp":"51","attack":"52","defense":"90"},
{"name":"Conkeldurr","type1":"Fighting","hp":"105","attack":"140","defense":"95"},
{"name":"Copperajah","type1":"Steel","hp":"122","attack":"130","defense":"69"},
{"name":"Corphish","type1":"Water","hp":"43","attack":"80","defense":"65"},
{"name":"Corsola","type1":"Water","hp":"55","attack":"55","defense":"85"},
{"name":"Corviknight","type1":"Flying","hp":"98","attack":"87","defense":"105"},
{"name":"Corvisquire","type1":"Flying","hp":"68","attack":"67","defense":"55"},
{"name":"Cosmoem","type1":"Psychic","hp":"43","attack":"29","defense":"131"},
{"name":"Cosmog","type1":"Psychic","hp":"43","attack":"29","defense":"31"},
{"name":"Cottonee","type1":"Grass","hp":"40","attack":"27","defense":"60"},
{"name":"Crabominable","type1":"Fighting","hp":"97","attack":"132","defense":"77"},
{"name":"Crabrawler","type1":"Fighting","hp":"47","attack":"82","defense":"57"},
{"name":"Cradily","type1":"Rock","hp":"86","attack":"81","defense":"97"},
{"name":"Cramorant","type1":"Flying","hp":"70","attack":"85","defense":"55"},
{"name":"Cranidos","type1":"Rock","hp":"67","attack":"125","defense":"40"},
{"name":"Crawdaunt","type1":"Water","hp":"63","attack":"120","defense":"85"},
{"name":"Cresselia","type1":"Psychic","hp":"120","attack":"70","defense":"120"},
{"name":"Croagunk","type1":"Poison","hp":"48","attack":"61","defense":"40"},
{"name":"Crobat","type1":"Poison","hp":"85","attack":"90","defense":"80"},
{"name":"Croconaw","type1":"Water","hp":"65","attack":"80","defense":"80"},
{"name":"Crustle","type1":"Bug","hp":"70","attack":"95","defense":"125"},
{"name":"Cryogonal","type1":"Ice","hp":"70","attack":"50","defense":"30"},
{"name":"Cubchoo","type1":"Ice","hp":"55","attack":"70","defense":"40"},
{"name":"Cubone","type1":"Ground","hp":"50","attack":"50","defense":"95"},
{"name":"Cufant","type1":"Steel","hp":"72","attack":"80","defense":"49"},
{"name":"Cursola","type1":"Ghost","hp":"60","attack":"95","defense":"50"},
{"name":"Cutiefly","type1":"Bug","hp":"40","attack":"45","defense":"40"},
{"name":"Cyndaquil","type1":"Fire","hp":"39","attack":"52","defense":"43"},
{"name":"Dada Zarude","type1":"Dark","hp":"105","attack":"120","defense":"105"},
{"name":"Darkrai","type1":"Dark","hp":"70","attack":"90","defense":"90"},
{"name":"Darmanitan Standard Mode","type1":"Fire","hp":"105","attack":"140","defense":"55"},
{"name":"Darmanitan Zen Mode","type1":"Fire","hp":"105","attack":"30","defense":"105"},
{"name":"Dartrix","type1":"Grass","hp":"78","attack":"75","defense":"75"},
{"name":"Darumaka","type1":"Fire","hp":"70","attack":"90","defense":"45"},
{"name":"Dawn Wings Necrozma","type1":"Psychic","hp":"97","attack":"113","defense":"109"},
{"name":"Decidueye","type1":"Grass","hp":"78","attack":"107","defense":"75"},
{"name":"Dedenne","type1":"Electric","hp":"67","attack":"58","defense":"57"},
{"name":"Deerling","type1":"Normal","hp":"60","attack":"60","defense":"50"},
{"name":"Deino","type1":"Dark","hp":"52","attack":"65","defense":"50"},
{"name":"Delcatty","type1":"Normal","hp":"70","attack":"65","defense":"65"},
{"name":"Delibird","type1":"Ice","hp":"45","attack":"55","defense":"45"},
{"name":"Delphox","type1":"Fire","hp":"75","attack":"69","defense":"72"},
{"name":"Deoxys Attack Forme","type1":"Psychic","hp":"50","attack":"180","defense":"20"},
{"name":"Deoxys Defense Forme","type1":"Psychic","hp":"50","attack":"70","defense":"160"},
{"name":"Deoxys Normal Forme","type1":"Psychic","hp":"50","attack":"150","defense":"50"},
{"name":"Deoxys Speed Forme","type1":"Psychic","hp":"50","attack":"95","defense":"90"},
{"name":"Dewgong","type1":"Water","hp":"90","attack":"70","defense":"80"},
{"name":"Dewott","type1":"Water","hp":"75","attack":"75","defense":"60"},
{"name":"Dewpider","type1":"Water","hp":"38","attack":"40","defense":"52"},
{"name":"Dhelmise","type1":"Ghost","hp":"70","attack":"131","defense":"100"},
{"name":"Dialga","type1":"Steel","hp":"100","attack":"120","defense":"120"},
{"name":"Diancie","type1":"Rock","hp":"50","attack":"100","defense":"150"},
{"name":"Diggersby","type1":"Normal","hp":"85","attack":"56","defense":"77"},
{"name":"Diglett","type1":"Ground","hp":"10","attack":"55","defense":"25"},
{"name":"Ditto","type1":"Normal","hp":"48","attack":"48","defense":"48"},
{"name":"Dodrio","type1":"Normal","hp":"60","attack":"110","defense":"70"},
{"name":"Doduo","type1":"Normal","hp":"35","attack":"85","defense":"45"},
{"name":"Donphan","type1":"Ground","hp":"90","attack":"120","defense":"120"},
{"name":"Dottler","type1":"Bug","hp":"50","attack":"35","defense":"80"},
{"name":"Doublade","type1":"Steel","hp":"59","attack":"110","defense":"150"},
{"name":"Dracovish","type1":"Water","hp":"90","attack":"90","defense":"100"},
{"name":"Dracozolt","type1":"Electric","hp":"90","attack":"100","defense":"90"},
{"name":"Dragalge","type1":"Poison","hp":"65","attack":"75","defense":"90"},
{"name":"Dragapult","type1":"Dragon","hp":"88","attack":"120","defense":"75"},
{"name":"Dragonair","type1":"Dragon","hp":"61","attack":"84","defense":"65"},
{"name":"Dragonite","type1":"Dragon","hp":"91","attack":"134","defense":"95"},
{"name":"Drakloak","type1":"Dragon","hp":"68","attack":"80","defense":"50"},
{"name":"Drampa","type1":"Normal","hp":"78","attack":"60","defense":"85"},
{"name":"Drapion","type1":"Poison","hp":"70","attack":"90","defense":"110"},
{"name":"Dratini","type1":"Dragon","hp":"41","attack":"64","defense":"45"},
{"name":"Drednaw","type1":"Water","hp":"90","attack":"115","defense":"90"},
{"name":"Dreepy","type1":"Dragon","hp":"28","attack":"60","defense":"30"},
{"name":"Drifblim","type1":"Ghost","hp":"150","attack":"80","defense":"44"},
{"name":"Drifloon","type1":"Ghost","hp":"90","attack":"50","defense":"34"},
{"name":"Drilbur","type1":"Ground","hp":"60","attack":"85","defense":"40"},
{"name":"Drizzile","type1":"Water","hp":"65","attack":"60","defense":"55"},
{"name":"Drowzee","type1":"Psychic","hp":"60","attack":"48","defense":"45"},
{"name":"Druddigon","type1":"Dragon","hp":"77","attack":"120","defense":"90"},
{"name":"Dubwool","type1":"Normal","hp":"72","attack":"80","defense":"100"},
{"name":"Ducklett","type1":"Water","hp":"62","attack":"44","defense":"50"},
{"name":"Dugtrio","type1":"Ground","hp":"35","attack":"80","defense":"50"},
{"name":"Dunsparce","type1":"Normal","hp":"100","attack":"70","defense":"70"},
{"name":"Duosion","type1":"Psychic","hp":"65","attack":"40","defense":"50"},
{"name":"Duraludon","type1":"Steel","hp":"70","attack":"95","defense":"115"},
{"name":"Durant","type1":"Bug","hp":"58","attack":"109","defense":"112"},
{"name":"Dusclops","type1":"Ghost","hp":"40","attack":"70","defense":"130"},
{"name":"Dusk Mane Necrozma","type1":"Psychic","hp":"97","attack":"157","defense":"127"},
{"name":"Dusknoir","type1":"Ghost","hp":"45","attack":"100","defense":"135"},
{"name":"Duskull","type1":"Ghost","hp":"20","attack":"40","defense":"90"},
{"name":"Dustox","type1":"Bug","hp":"60","attack":"50","defense":"70"},
{"name":"Dwebble","type1":"Bug","hp":"50","attack":"65","defense":"85"},
{"name":"Eelektrik","type1":"Electric","hp":"65","attack":"85","defense":"70"},
{"name":"Eelektross","type1":"Electric","hp":"85","attack":"115","defense":"80"},
{"name":"Eevee","type1":"Normal","hp":"55","attack":"55","defense":"50"},
{"name":"Eiscue Ice Face","type1":"Ice","hp":"75","attack":"80","defense":"110"},
{"name":"Eiscue Noice Face","type1":"Ice","hp":"75","attack":"80","defense":"70"},
{"name":"Ekans","type1":"Poison","hp":"35","attack":"60","defense":"44"},
{"name":"Eldegoss","type1":"Graass","hp":"60","attack":"50","defense":"90"},
{"name":"Electabuzz","type1":"Electric","hp":"65","attack":"83","defense":"57"},
{"name":"Electivire","type1":"Electric","hp":"75","attack":"123","defense":"67"},
{"name":"Electrike","type1":"Electric","hp":"40","attack":"45","defense":"40"},
{"name":"Electrode","type1":"Electric","hp":"60","attack":"50","defense":"70"},
{"name":"Elekid","type1":"Electric","hp":"45","attack":"63","defense":"37"},
{"name":"Elgyem","type1":"Psychic","hp":"55","attack":"55","defense":"55"},
{"name":"Emboar","type1":"Fire","hp":"110","attack":"123","defense":"65"},
{"name":"Emolga","type1":"Electric","hp":"55","attack":"75","defense":"60"},
{"name":"Empoleon","type1":"Water","hp":"84","attack":"86","defense":"88"},
{"name":"Entei","type1":"Fire","hp":"115","attack":"115","defense":"85"},
{"name":"Escavalier","type1":"Bug","hp":"70","attack":"135","defense":"105"},
{"name":"Espeon","type1":"Psychic","hp":"65","attack":"65","defense":"60"},
{"name":"Espurr","type1":"Psychic","hp":"62","attack":"48","defense":"54"},
{"name":"Eternamax Eternatus","type1":"Poison","hp":"255","attack":"115","defense":"250"},
{"name":"Eternatus","type1":"Poison","hp":"140","attack":"85","defense":"95"},
{"name":"Excadrill","type1":"Ground","hp":"110","attack":"135","defense":"60"},
{"name":"Exeggcute","type1":"Grass","hp":"60","attack":"40","defense":"80"},
{"name":"Exeggutor","type1":"Grass","hp":"95","attack":"95","defense":"85"},
{"name":"Exploud","type1":"Normal","hp":"104","attack":"91","defense":"63"},
{"name":"Falinks","type1":"Fighting","hp":"65","attack":"100","defense":"100"},
{"name":"Fan Rotom","type1":"Electric","hp":"50","attack":"65","defense":"107"},
{"name":"Farfetch'd","type1":"Normal","hp":"52","attack":"90","defense":"55"},
{"name":"Fearow","type1":"Normal","hp":"65","attack":"90","defense":"65"},
{"name":"Feebas","type1":"Water","hp":"20","attack":"15","defense":"20"},
{"name":"Fennekin","type1":"Fire","hp":"40","attack":"45","defense":"40"},
{"name":"Feraligatr","type1":"Water","hp":"85","attack":"105","defense":"100"},
{"name":"Ferroseed","type1":"Grass","hp":"44","attack":"50","defense":"91"},
{"name":"Ferrothorn","type1":"Grass","hp":"74","attack":"94","defense":"131"},
{"name":"Finneon","type1":"Water","hp":"49","attack":"49","defense":"56"},
{"name":"Flaaffy","type1":"Electric","hp":"70","attack":"55","defense":"55"},
{"name":"Flabébé","type1":"Fairy","hp":"44","attack":"38","defense":"39"},
{"name":"Flapple","type1":"Grass","hp":"70","attack":"110","defense":"80"},
{"name":"Flareon","type1":"Fire","hp":"65","attack":"130","defense":"60"},
{"name":"Fletchinder","type1":"Fire","hp":"62","attack":"73","defense":"55"},
{"name":"Fletchling","type1":"Normal","hp":"45","attack":"50","defense":"43"},
{"name":"Floatzel","type1":"Water","hp":"85","attack":"105","defense":"55"},
{"name":"Floette","type1":"Fairy","hp":"54","attack":"45","defense":"47"},
{"name":"Florges","type1":"Fairy","hp":"78","attack":"65","defense":"68"},
{"name":"Flygon","type1":"Ground","hp":"80","attack":"100","defense":"80"},
{"name":"Fomantis","type1":"Grass","hp":"40","attack":"55","defense":"35"},
{"name":"Foongus","type1":"Grass","hp":"69","attack":"55","defense":"45"},
{"name":"Forretress","type1":"Bug","hp":"75","attack":"90","defense":"140"},
{"name":"Fraxure","type1":"Dragon","hp":"66","attack":"117","defense":"70"},
{"name":"Frillish","type1":"Water","hp":"55","attack":"40","defense":"50"},
{"name":"Froakie","type1":"Water","hp":"41","attack":"56","defense":"40"},
{"name":"Frogadier","type1":"Water","hp":"54","attack":"63","defense":"52"},
{"name":"Froslass","type1":"Ice","hp":"70","attack":"80","defense":"70"},
{"name":"Frosmoth","type1":"Ice","hp":"70","attack":"65","defense":"60"},
{"name":"Frost Rotom","type1":"Electric","hp":"50","attack":"65","defense":"107"},
{"name":"Furfrou","type1":"Normal","hp":"75","attack":"80","defense":"60"},
{"name":"Furret","type1":"Normal","hp":"85","attack":"76","defense":"64"},
{"name":"Gabite","type1":"Dragon","hp":"68","attack":"90","defense":"65"},
{"name":"Galarian Articuno","type1":"Psychic","hp":"90","attack":"85","defense":"85"},
{"name":"Galarian Corsola","type1":"Ghost","hp":"60","attack":"55","defense":"100"},
{"name":"Galarian Darmanitan Standard Mode","type1":"Ice","hp":"105","attack":"140","defense":"55"},
{"name":"Galarian Darmanitan Zen Mode","type1":"Ice","hp":"105","attack":"160","defense":"55"},
{"name":"Galarian Darumaka","type1":"Ice","hp":"70","attack":"90","defense":"45"},
{"name":"Galarian Farfetched","type1":"Fighting","hp":"52","attack":"95","defense":"55"},
{"name":"Galarian Linoone","type1":"Dark","hp":"78","attack":"70","defense":"61"},
{"name":"Galarian Meowth","type1":"Steel","hp":"50","attack":"65","defense":"55"},
{"name":"Galarian Moltres","type1":"Dark","hp":"90","attack":"85","defense":"90"},
{"name":"Galarian Mr. Mime","type1":"Ice","hp":"50","attack":"65","defense":"65"},
{"name":"Galarian Ponyta","type1":"Psychic","hp":"50","attack":"85","defense":"55"},
{"name":"Galarian Rapidash","type1":"Psychic","hp":"65","attack":"100","defense":"70"},
{"name":"Galarian Slowbro","type1":"Poison","hp":"95","attack":"100","defense":"95"},
{"name":"Galarian Slowking","type1":"Poison","hp":"95","attack":"65","defense":"80"},
{"name":"Galarian Slowpoke","type1":"Psychic","hp":"90","attack":"65","defense":"65"},
{"name":"Galarian Stunfisk","type1":"Ground","hp":"109","attack":"81","defense":"99"},
{"name":"Galarian Weezing","type1":"Poison","hp":"65","attack":"90","defense":"120"},
{"name":"Galarian Yamask","type1":"Ground","hp":"38","attack":"55","defense":"85"},
{"name":"Galarian Zapdos","type1":"Fighting","hp":"90","attack":"125","defense":"90"},
{"name":"Galarian Zigzagoon","type1":"Dark","hp":"38","attack":"30","defense":"41"},
{"name":"Gallade","type1":"Psychic","hp":"68","attack":"125","defense":"65"},
{"name":"Galvantula","type1":"Bug","hp":"70","attack":"77","defense":"60"},
{"name":"Garbodor","type1":"Poison","hp":"80","attack":"95","defense":"82"},
{"name":"Garchomp","type1":"Dragon","hp":"108","attack":"130","defense":"95"},
{"name":"Gardevoir","type1":"Psychic","hp":"68","attack":"65","defense":"65"},
{"name":"Gastly","type1":"Ghost","hp":"30","attack":"35","defense":"30"},
{"name":"Gastrodon","type1":"Water","hp":"111","attack":"83","defense":"68"},
{"name":"Genesect","type1":"Bug","hp":"71","attack":"120","defense":"95"},
{"name":"Gengar","type1":"Ghost","hp":"60","attack":"65","defense":"60"},
{"name":"Geodude","type1":"Rock","hp":"40","attack":"80","defense":"100"},
{"name":"Gible","type1":"Dragon","hp":"58","attack":"70","defense":"45"},
{"name":"Gigalith","type1":"Rock","hp":"85","attack":"135","defense":"130"},
{"name":"Gigantamax Alcremie","type1":"Fairy","hp":"65","attack":"60","defense":"75"},
{"name":"Gigantamax Appletun","type1":"Grass","hp":"110","attack":"85","defense":"80"},
{"name":"Gigantamax Blasoise","type1":"Blastoise","hp":"79","attack":"83","defense":"100"},
{"name":"Gigantamax Butterfree","type1":"Bug","hp":"60","attack":"45","defense":"50"},
{"name":"Gigantamax Centiskorch","type1":"Fire","hp":"100","attack":"115","defense":"65"},
{"name":"Gigantamax Charizard","type1":"Fire","hp":"78","attack":"84","defense":"78"},
{"name":"Gigantamax Cinderace","type1":"Fire","hp":"80","attack":"116","defense":"75"},
{"name":"Gigantamax Coalossal","type1":"Rock","hp":"110","attack":"80","defense":"120"},
{"name":"Gigantamax Copperajah","type1":"Steel","hp":"122","attack":"130","defense":"69"},
{"name":"Gigantamax Corviknight","type1":"Flying","hp":"98","attack":"87","defense":"105"},
{"name":"Gigantamax Drednaw","type1":"Water","hp":"90","attack":"115","defense":"90"},
{"name":"Gigantamax Duraludon","type1":"Steel","hp":"70","attack":"95","defense":"115"},
{"name":"Gigantamax Eevee","type1":"Normal","hp":"55","attack":"55","defense":"50"},
{"name":"Gigantamax Flapple","type1":"Grass","hp":"70","attack":"110","defense":"80"},
{"name":"Gigantamax Garbodor","type1":"Poison","hp":"80","attack":"95","defense":"82"},
{"name":"Gigantamax Gengar","type1":"Ghost","hp":"60","attack":"65","defense":"60"},
{"name":"Gigantamax Grimmsnarl","type1":"Dark","hp":"95","attack":"120","defense":"65"},
{"name":"Gigantamax Hatterene","type1":"Psychic","hp":"57","attack":"90","defense":"95"},
{"name":"Gigantamax Inteleon","type1":"Water","hp":"70","attack":"85","defense":"65"},
{"name":"Gigantamax Kingler","type1":"Water","hp":"55","attack":"130","defense":"115"},
{"name":"Gigantamax Lapras","type1":"Water","hp":"130","attack":"85","defense":"80"},
{"name":"Gigantamax Machamp","type1":"Fighting","hp":"90","attack":"130","defense":"80"},
{"name":"Gigantamax Melmetal","type1":"Steel","hp":"135","attack":"143","defense":"143"},
{"name":"Gigantamax Meowth","type1":"Normal","hp":"40","attack":"45","defense":"35"},
{"name":"Gigantamax Orbeetle","type1":"Bug","hp":"60","attack":"45","defense":"110"},
{"name":"Gigantamax Pikachu","type1":"Electric","hp":"35","attack":"55","defense":"40"},
{"name":"Gigantamax Rillaboom","type1":"Grass","hp":"100","attack":"125","defense":"90"},
{"name":"Gigantamax Sandaconda","type1":"Ground","hp":"72","attack":"107","defense":"125"},
{"name":"Gigantamax Snorlax","type1":"Normal","hp":"160","attack":"110","defense":"65"},
{"name":"Gigantamax Toxitricity","type1":"Electric","hp":"75","attack":"98","defense":"70"},
{"name":"Gigantamax Urshifu Rapid Strike Style","type1":"Fighting","hp":"100","attack":"130","defense":"100"},
{"name":"Gigantamax Urshifu Single Strike Style","type1":"Fighting","hp":"100","attack":"130","defense":"100"},
{"name":"Gigantamax Venusaur","type1":"Grass","hp":"80","attack":"82","defense":"83"},
{"name":"Girafarig","type1":"Normal","hp":"70","attack":"80","defense":"65"},
{"name":"Giratina Altered Forme","type1":"Ghost","hp":"150","attack":"100","defense":"120"},
{"name":"Giratina Origin Forme","type1":"Ghost","hp":"150","attack":"120","defense":"100"},
{"name":"Glaceon","type1":"Ice","hp":"65","attack":"60","defense":"110"},
{"name":"Glalie","type1":"Ice","hp":"80","attack":"80","defense":"80"},
{"name":"Glameow","type1":"Normal","hp":"49","attack":"55","defense":"42"},
{"name":"Glastrier","type1":"Ice","hp":"100","attack":"145","defense":"130"},
{"name":"Gligar","type1":"Ground","hp":"65","attack":"75","defense":"105"},
{"name":"Gliscor","type1":"Ground","hp":"75","attack":"95","defense":"125"},
{"name":"Gloom","type1":"Grass","hp":"60","attack":"65","defense":"70"},
{"name":"Gogoat","type1":"Grass","hp":"123","attack":"100","defense":"62"},
{"name":"Golbat","type1":"Poison","hp":"75","attack":"80","defense":"70"},
{"name":"Goldeen","type1":"Water","hp":"45","attack":"67","defense":"60"},
{"name":"Golduck","type1":"Water","hp":"80","attack":"82","defense":"78"},
{"name":"Golem","type1":"Rock","hp":"80","attack":"120","defense":"130"},
{"name":"Golett","type1":"Ground","hp":"59","attack":"74","defense":"50"},
{"name":"Golisopod","type1":"Bug","hp":"75","attack":"125","defense":"140"},
{"name":"Golurk","type1":"Ground","hp":"89","attack":"124","defense":"80"},
{"name":"Goodra","type1":"Dragon","hp":"90","attack":"100","defense":"70"},
{"name":"Goomy","type1":"Dragon","hp":"45","attack":"50","defense":"35"},
{"name":"Gorebyss","type1":"Water","hp":"55","attack":"84","defense":"105"},
{"name":"Gossifleur","type1":"Grass","hp":"40","attack":"40","defense":"60"},
{"name":"Gothita","type1":"Psychic","hp":"45","attack":"30","defense":"50"},
{"name":"Gothitelle","type1":"Psychic","hp":"70","attack":"55","defense":"95"},
{"name":"Gothorita","type1":"Psychic","hp":"60","attack":"45","defense":"70"},
{"name":"Gourgeist Average Size","type1":"Ghost","hp":"65","attack":"90","defense":"122"},
{"name":"Gourgeist Large Size","type1":"Ghost","hp":"75","attack":"95","defense":"122"},
{"name":"Gourgeist Small Size","type1":"Ghost","hp":"55","attack":"85","defense":"122"},
{"name":"Gourgeist Super Size","type1":"Ghost","hp":"85","attack":"100","defense":"122"},
{"name":"Granbull","type1":"Fairy","hp":"90","attack":"120","defense":"75"},
{"name":"Grapploct","type1":"Fighting","hp":"80","attack":"118","defense":"90"},
{"name":"Graveler","type1":"Rock","hp":"55","attack":"95","defense":"115"},
{"name":"Greedent","type1":"Normal","hp":"120","attack":"95","defense":"95"},
{"name":"Greninja","type1":"Water","hp":"72","attack":"95","defense":"67"},
{"name":"Grimer","type1":"Poison","hp":"80","attack":"80","defense":"50"},
{"name":"Grimmsnarl","type1":"Dark","hp":"95","attack":"120","defense":"65"},
{"name":"Grookey","type1":"Grass","hp":"50","attack":"65","defense":"50"},
{"name":"Grotle","type1":"Grass","hp":"75","attack":"89","defense":"85"},
{"name":"Groudon","type1":"Ground","hp":"100","attack":"150","defense":"140"},
{"name":"Grovyle","type1":"Grass","hp":"50","attack":"65","defense":"45"},
{"name":"Growlithe","type1":"Fire","hp":"55","attack":"70","defense":"45"},
{"name":"Grubbin","type1":"Bug","hp":"47","attack":"62","defense":"45"},
{"name":"Grumpig","type1":"Psychic","hp":"80","attack":"45","defense":"65"},
{"name":"Gulpin","type1":"Poison","hp":"70","attack":"43","defense":"53"},
{"name":"Gumshoos","type1":"Normal","hp":"88","attack":"110","defense":"60"},
{"name":"Gurdurr","type1":"Fighting","hp":"85","attack":"105","defense":"85"},
{"name":"Guzzlord","type1":"Dark","hp":"223","attack":"101","defense":"53"},
{"name":"Gyarados","type1":"Water","hp":"95","attack":"125","defense":"79"},
{"name":"Hakamo-o","type1":"Dragon","hp":"55","attack":"75","defense":"90"},
{"name":"Happiny","type1":"Normal","hp":"100","attack":"5","defense":"5"},
{"name":"Hariyama","type1":"Fighting","hp":"144","attack":"120","defense":"60"},
{"name":"Hatenna","type1":"Psychic","hp":"42","attack":"30","defense":"45"},
{"name":"Hatterene","type1":"Psychic","hp":"57","attack":"90","defense":"95"},
{"name":"Hattrem","type1":"Psychic","hp":"57","attack":"40","defense":"65"},
{"name":"Haunter","type1":"Ghost","hp":"45","attack":"50","defense":"45"},
{"name":"Hawlucha","type1":"Fighting","hp":"78","attack":"92","defense":"75"},
{"name":"Haxorus","type1":"Dragon","hp":"76","attack":"147","defense":"90"},
{"name":"Heat Rotom","type1":"Electric","hp":"50","attack":"65","defense":"107"},
{"name":"Heatmor","type1":"Fire","hp":"85","attack":"97","defense":"66"},
{"name":"Heatran","type1":"Fire","hp":"91","attack":"90","defense":"106"},
{"name":"Heliolisk","type1":"Electric","hp":"62","attack":"55","defense":"52"},
{"name":"Helioptile","type1":"Electric","hp":"44","attack":"38","defense":"33"},
{"name":"Heracross","type1":"Bug","hp":"80","attack":"125","defense":"75"},
{"name":"Herdier","type1":"Normal","hp":"65","attack":"80","defense":"65"},
{"name":"Hippopotas","type1":"Ground","hp":"68","attack":"72","defense":"78"},
{"name":"Hippowdon","type1":"Ground","hp":"108","attack":"112","defense":"118"},
{"name":"Hitmonchan","type1":"Fighting","hp":"50","attack":"105","defense":"79"},
{"name":"Hitmonlee","type1":"Fighting","hp":"50","attack":"120","defense":"53"},
{"name":"Hitmontop","type1":"Fighting","hp":"50","attack":"95","defense":"95"},
{"name":"Ho-oh","type1":"Fire","hp":"106","attack":"130","defense":"90"},
{"name":"Honchkrow","type1":"Dark","hp":"100","attack":"125","defense":"52"},
{"name":"Honedge","type1":"Steel","hp":"45","attack":"80","defense":"100"},
{"name":"Hoopa Confined","type1":"Psychic","hp":"80","attack":"110","defense":"60"},
{"name":"Hoopa Unbound","type1":"Psychic","hp":"80","attack":"160","defense":"60"},
{"name":"Hoothoot","type1":"Normal","hp":"60","attack":"30","defense":"30"},
{"name":"Hoppip","type1":"Grass","hp":"35","attack":"35","defense":"40"},
{"name":"Horsea","type1":"Water","hp":"30","attack":"40","defense":"70"},
{"name":"Houndoom","type1":"Dark","hp":"75","attack":"90","defense":"50"},
{"name":"Houndour","type1":"Dark","hp":"45","attack":"60","defense":"30"},
{"name":"Huntail","type1":"Water","hp":"55","attack":"104","defense":"105"},
{"name":"Hydreigon","type1":"Dark","hp":"92","attack":"105","defense":"90"},
{"name":"Hypno","type1":"Psychic","hp":"85","attack":"73","defense":"70"},
{"name":"Ice Rider Calyrex","type1":"Psychic","hp":"100","attack":"165","defense":"150"},
{"name":"Igglybuff","type1":"Normal","hp":"90","attack":"30","defense":"15"},
{"name":"Illumise","type1":"Bug","hp":"65","attack":"47","defense":"55"},
{"name":"Impidimp","type1":"Dark","hp":"45","attack":"45","defense":"30"},
{"name":"Incineroar","type1":"Fire","hp":"95","attack":"115","defense":"90"},
{"name":"Indeedee Female","type1":"Psychic","hp":"70","attack":"55","defense":"65"},
{"name":"Indeedee Male","type1":"Psychic","hp":"60","attack":"65","defense":"55"},
{"name":"Infernape","type1":"Fire","hp":"76","attack":"104","defense":"71"},
{"name":"Inkay","type1":"Dark","hp":"53","attack":"54","defense":"53"},
{"name":"Inteleon","type1":"Water","hp":"70","attack":"85","defense":"65"},
{"name":"Ivysaur","type1":"Grass","hp":"60","attack":"62","defense":"63"},
{"name":"Jangmo-o","type1":"Dragon","hp":"45","attack":"55","defense":"65"},
{"name":"Jellicent","type1":"Water","hp":"100","attack":"60","defense":"70"},
{"name":"Jigglypuff","type1":"Normal","hp":"115","attack":"45","defense":"20"},
{"name":"Jirachi","type1":"Steel","hp":"100","attack":"100","defense":"100"},
{"name":"Jolteon","type1":"Electric","hp":"65","attack":"65","defense":"60"},
{"name":"Joltik","type1":"Bug","hp":"50","attack":"47","defense":"50"},
{"name":"Jumpluff","type1":"Grass","hp":"75","attack":"55","defense":"70"},
{"name":"Jynx","type1":"Ice","hp":"65","attack":"50","defense":"35"},
{"name":"Kabuto","type1":"Rock","hp":"30","attack":"80","defense":"90"},
{"name":"Kabutops","type1":"Rock","hp":"60","attack":"115","defense":"105"},
{"name":"Kadabra","type1":"Psychic","hp":"40","attack":"35","defense":"30"},
{"name":"Kakuna","type1":"Bug","hp":"45","attack":"25","defense":"50"},
{"name":"Kangaskhan","type1":"Normal","hp":"105","attack":"95","defense":"80"},
{"name":"Karrablast","type1":"Bug","hp":"50","attack":"75","defense":"45"},
{"name":"Kartana","type1":"Grass","hp":"59","attack":"181","defense":"131"},
{"name":"Kecleon","type1":"Normal","hp":"60","attack":"90","defense":"70"},
{"name":"Keldeo Ordinary Forme","type1":"Water","hp":"91","attack":"72","defense":"90"},
{"name":"Keldeo Resolute Forme","type1":"Water","hp":"91","attack":"72","defense":"90"},
{"name":"Kingdra","type1":"Water","hp":"75","attack":"95","defense":"95"},
{"name":"Kingler","type1":"Water","hp":"55","attack":"130","defense":"115"},
{"name":"Kirlia","type1":"Psychic","hp":"38","attack":"35","defense":"35"},
{"name":"Klang","type1":"Steel","hp":"60","attack":"80","defense":"95"},
{"name":"Klefki","type1":"Steel","hp":"57","attack":"80","defense":"91"},
{"name":"Klink","type1":"Steel","hp":"40","attack":"55","defense":"70"},
{"name":"Klinklang","type1":"Steel","hp":"60","attack":"100","defense":"115"},
{"name":"Koffing","type1":"Poison","hp":"40","attack":"65","defense":"95"},
{"name":"Komala","type1":"Normal","hp":"65","attack":"115","defense":"65"},
{"name":"Kommo-o","type1":"Dragon","hp":"75","attack":"110","defense":"125"},
{"name":"Krabby","type1":"Water","hp":"30","attack":"105","defense":"90"},
{"name":"Kricketot","type1":"Bug","hp":"37","attack":"25","defense":"41"},
{"name":"Kricketune","type1":"Bug","hp":"77","attack":"85","defense":"51"},
{"name":"Krokorok","type1":"Ground","hp":"60","attack":"82","defense":"45"},
{"name":"Krookodile","type1":"Ground","hp":"95","attack":"117","defense":"80"},
{"name":"Kubfu","type1":"Fighting","hp":"60","attack":"90","defense":"60"},
{"name":"Kyogre","type1":"Water","hp":"100","attack":"100","defense":"90"},
{"name":"Kyurem","type1":"Dragon","hp":"125","attack":"130","defense":"90"},
{"name":"Lairon","type1":"Steel","hp":"60","attack":"90","defense":"140"},
{"name":"Lampent","type1":"Ghost","hp":"60","attack":"40","defense":"60"},
{"name":"Landorus Incarnate Forme","type1":"Ground","hp":"89","attack":"125","defense":"90"},
{"name":"Landorus Therian Forme","type1":"Ground","hp":"89","attack":"145","defense":"90"},
{"name":"Lanturn","type1":"Water","hp":"125","attack":"58","defense":"58"},
{"name":"Lapras","type1":"Water","hp":"130","attack":"85","defense":"80"},
{"name":"Larvesta","type1":"Bug","hp":"55","attack":"85","defense":"55"},
{"name":"Larvitar","type1":"Rock","hp":"50","attack":"64","defense":"50"},
{"name":"Latias","type1":"Dragon","hp":"80","attack":"80","defense":"90"},
{"name":"Latios","type1":"Dragon","hp":"80","attack":"90","defense":"80"},
{"name":"Leafeon","type1":"Grass","hp":"65","attack":"110","defense":"130"},
{"name":"Leavanny","type1":"Bug","hp":"75","attack":"103","defense":"80"},
{"name":"Ledian","type1":"Bug","hp":"55","attack":"35","defense":"50"},
{"name":"Ledyba","type1":"Bug","hp":"40","attack":"20","defense":"30"},
{"name":"Lickilicky","type1":"Normal","hp":"110","attack":"85","defense":"95"},
{"name":"Lickitung","type1":"Normal","hp":"90","attack":"55","defense":"75"},
{"name":"Liepard","type1":"Dark","hp":"64","attack":"88","defense":"50"},
{"name":"Lileep","type1":"Rock","hp":"66","attack":"41","defense":"77"},
{"name":"Lilligant","type1":"Grass","hp":"70","attack":"60","defense":"75"},
{"name":"Lillipup","type1":"Normal","hp":"45","attack":"60","defense":"45"},
{"name":"Linoone","type1":"Normal","hp":"78","attack":"70","defense":"61"},
{"name":"Litleo","type1":"Fire","hp":"62","attack":"50","defense":"58"},
{"name":"Litten","type1":"Fire","hp":"45","attack":"65","defense":"40"},
{"name":"Litwick","type1":"Ghost","hp":"50","attack":"30","defense":"55"},
{"name":"Lombre","type1":"Water","hp":"60","attack":"50","defense":"50"},
{"name":"Lopunny","type1":"Normal","hp":"65","attack":"76","defense":"84"},
{"name":"Lotad","type1":"Water","hp":"40","attack":"30","defense":"30"},
{"name":"Loudred","type1":"Normal","hp":"84","attack":"71","defense":"43"},
{"name":"Lucario","type1":"Fighting","hp":"70","attack":"110","defense":"70"},
{"name":"Ludicolo","type1":"Water","hp":"80","attack":"70","defense":"70"},
{"name":"Lugia","type1":"Psychic","hp":"106","attack":"90","defense":"130"},
{"name":"Lumineon","type1":"Water","hp":"69","attack":"69","defense":"76"},
{"name":"Lunala","type1":"Psychic","hp":"137","attack":"113","defense":"89"},
{"name":"Lunatone","type1":"Rock","hp":"70","attack":"55","defense":"65"},
{"name":"Lurantis","type1":"Grass","hp":"70","attack":"105","defense":"90"},
{"name":"Luvdisc","type1":"Water","hp":"43","attack":"30","defense":"55"},
{"name":"Luxio","type1":"Electric","hp":"60","attack":"85","defense":"49"},
{"name":"Luxray","type1":"Electric","hp":"80","attack":"120","defense":"79"},
{"name":"Lycanroc Dusk Forme","type1":"Rock","hp":"75","attack":"117","defense":"65"},
{"name":"Lycanroc Midday Forme","type1":"Rock","hp":"75","attack":"115","defense":"65"},
{"name":"Lycanroc Midnight Forme","type1":"Rock","hp":"85","attack":"115","defense":"75"},
{"name":"Machamp","type1":"Fighting","hp":"90","attack":"130","defense":"80"},
{"name":"Machoke","type1":"Fighting","hp":"80","attack":"100","defense":"70"},
{"name":"Machop","type1":"Fighting","hp":"70","attack":"80","defense":"50"},
{"name":"Magby","type1":"Fire","hp":"45","attack":"75","defense":"37"},
{"name":"Magcargo","type1":"Fire","hp":"50","attack":"50","defense":"120"},
{"name":"Magearna","type1":"Steel","hp":"80","attack":"95","defense":"115"},
{"name":"Magikarp","type1":"Water","hp":"20","attack":"10","defense":"55"},
{"name":"Magmar","type1":"Fire","hp":"65","attack":"95","defense":"57"},
{"name":"Magmortar","type1":"Fire","hp":"75","attack":"95","defense":"67"},
{"name":"Magnemite","type1":"Electric","hp":"25","attack":"35","defense":"70"},
{"name":"Magneton","type1":"Electric","hp":"50","attack":"60","defense":"95"},
{"name":"Magnezone","type1":"Electric","hp":"70","attack":"70","defense":"115"},
{"name":"Makuhita","type1":"Fighting","hp":"72","attack":"60","defense":"30"},
{"name":"Malamar","type1":"Dark","hp":"86","attack":"92","defense":"88"},
{"name":"Mamoswine","type1":"Ice","hp":"110","attack":"130","defense":"80"},
{"name":"Manaphy","type1":"Water","hp":"100","attack":"100","defense":"100"},
{"name":"Mandibuzz","type1":"Dark","hp":"110","attack":"65","defense":"105"},
{"name":"Manectric","type1":"Electric","hp":"70","attack":"75","defense":"60"},
{"name":"Mankey","type1":"Fighting","hp":"40","attack":"80","defense":"35"},
{"name":"Mantine","type1":"Water","hp":"65","attack":"40","defense":"70"},
{"name":"Mantyke","type1":"Water","hp":"45","attack":"20","defense":"50"},
{"name":"Maractus","type1":"Grass","hp":"75","attack":"86","defense":"67"},
{"name":"Mareanie","type1":"Poison","hp":"50","attack":"53","defense":"62"},
{"name":"Mareep","type1":"Electric","hp":"55","attack":"40","defense":"40"},
{"name":"Marill","type1":"Water","hp":"70","attack":"20","defense":"50"},
{"name":"Marowak","type1":"Ground","hp":"60","attack":"80","defense":"110"},
{"name":"Marshadow","type1":"Fighting","hp":"90","attack":"125","defense":"80"},
{"name":"Marshtomp","type1":"Water","hp":"70","attack":"85","defense":"70"},
{"name":"Masquerain","type1":"Bug","hp":"70","attack":"60","defense":"62"},
{"name":"Mawile","type1":"Steel","hp":"50","attack":"85","defense":"85"},
{"name":"Medicham","type1":"Fighting","hp":"60","attack":"60","defense":"75"},
{"name":"Meditite","type1":"Fighting","hp":"30","attack":"40","defense":"55"},
{"name":"Mega Abomasnow","type1":"Grass","hp":"90","attack":"132","defense":"105"},
{"name":"Mega Absol","type1":"Dark","hp":"65","attack":"150","defense":"60"},
{"name":"Mega Aerodactyl","type1":"Rock","hp":"80","attack":"135","defense":"85"},
{"name":"Mega Aggron","type1":"Steel","hp":"70","attack":"140","defense":"230"},
{"name":"Mega Alakazam","type1":"Psychic","hp":"55","attack":"50","defense":"65"},
{"name":"Mega Altaria","type1":"Dragon","hp":"75","attack":"110","defense":"110"},
{"name":"Mega Ampharos","type1":"Electric","hp":"90","attack":"95","defense":"105"},
{"name":"Mega Audino","type1":"Normal","hp":"103","attack":"60","defense":"126"},
{"name":"Mega Banette","type1":"Ghost","hp":"64","attack":"165","defense":"75"},
{"name":"Mega Beedrill","type1":"Bug","hp":"65","attack":"150","defense":"40"},
{"name":"Mega Blastoise","type1":"Water","hp":"79","attack":"103","defense":"120"},
{"name":"Mega Blaziken","type1":"Fire","hp":"80","attack":"160","defense":"80"},
{"name":"Mega Camerupt","type1":"Fire","hp":"70","attack":"120","defense":"100"},
{"name":"Mega Charizard X","type1":"Fire","hp":"78","attack":"130","defense":"111"},
{"name":"Mega Charizard Y","type1":"Fire","hp":"78","attack":"104","defense":"78"},
{"name":"Mega Diancie","type1":"Rock","hp":"50","attack":"160","defense":"110"},
{"name":"Mega Gallade","type1":"Psychic","hp":"68","attack":"165","defense":"95"},
{"name":"Mega Garchomp","type1":"Dragon","hp":"108","attack":"170","defense":"115"},
{"name":"Mega Gardevoir","type1":"Psychic","hp":"68","attack":"85","defense":"65"},
{"name":"Mega Gengar","type1":"Ghost","hp":"60","attack":"65","defense":"80"},
{"name":"Mega Glalie","type1":"Ice","hp":"80","attack":"120","defense":"80"},
{"name":"Mega Gyarados","type1":"Water","hp":"95","attack":"155","defense":"109"},
{"name":"Mega Heracross","type1":"Bug","hp":"80","attack":"185","defense":"115"},
{"name":"Mega Houndoom","type1":"Dark","hp":"75","attack":"90","defense":"90"},
{"name":"Mega Kangaskhan","type1":"Normal","hp":"105","attack":"125","defense":"100"},
{"name":"Mega Latias","type1":"Dragon","hp":"80","attack":"100","defense":"120"},
{"name":"Mega Latios","type1":"Dragon","hp":"80","attack":"130","defense":"100"},
{"name":"Mega Lopunny","type1":"Normal","hp":"65","attack":"136","defense":"94"},
{"name":"Mega Lucario","type1":"Fighting","hp":"70","attack":"145","defense":"88"},
{"name":"Mega Manectric","type1":"Electric","hp":"70","attack":"75","defense":"80"},
{"name":"Mega Mawile","type1":"Steel","hp":"50","attack":"105","defense":"125"},
{"name":"Mega Medicham","type1":"Fighting","hp":"60","attack":"100","defense":"85"},
{"name":"Mega Metagross","type1":"Steel","hp":"80","attack":"145","defense":"150"},
{"name":"Mega Mewtwo X","type1":"Psychic","hp":"106","attack":"190","defense":"100"},
{"name":"Mega Mewtwo Y","type1":"Psychic","hp":"106","attack":"150","defense":"70"},
{"name":"Mega Pidgeot","type1":"Normal","hp":"83","attack":"80","defense":"80"},
{"name":"Mega Pinsir","type1":"Bug","hp":"65","attack":"155","defense":"120"},
{"name":"Mega Rayquaza","type1":"Dragon","hp":"105","attack":"180","defense":"100"},
{"name":"Mega Sableye","type1":"Dark","hp":"50","attack":"85","defense":"125"},
{"name":"Mega Salamence","type1":"Dragon","hp":"95","attack":"145","defense":"130"},
{"name":"Mega Sceptile","type1":"Grass","hp":"70","attack":"110","defense":"75"},
{"name":"Mega Scizor","type1":"Bug","hp":"70","attack":"150","defense":"140"},
{"name":"Mega Sharpedo","type1":"Water","hp":"70","attack":"140","defense":"70"},
{"name":"Mega Slowbro","type1":"Water","hp":"95","attack":"75","defense":"180"},
{"name":"Mega Steelix","type1":"Steel","hp":"75","attack":"125","defense":"230"},
{"name":"Mega Swampert","type1":"Water","hp":"100","attack":"150","defense":"110"},
{"name":"Mega Tyranitar","type1":"Rock","hp":"100","attack":"164","defense":"150"},
{"name":"Mega Venusaur","type1":"Grass","hp":"80","attack":"100","defense":"123"},
{"name":"Meganium","type1":"Grass","hp":"80","attack":"82","defense":"100"},
{"name":"Melmetal","type1":"Steel","hp":"135","attack":"143","defense":"143"},
{"name":"Meloetta Aria Forme","type1":"Normal","hp":"100","attack":"77","defense":"77"},
{"name":"Meloetta Pirouette Forme","type1":"Normal","hp":"100","attack":"128","defense":"90"},
{"name":"Meltan","type1":"Steel","hp":"46","attack":"65","defense":"65"},
{"name":"Meowstic Female","type1":"Psychic","hp":"74","attack":"48","defense":"76"},
{"name":"Meowstic Male","type1":"Psychic","hp":"74","attack":"48","defense":"76"},
{"name":"Meowth","type1":"Normal","hp":"40","attack":"45","defense":"35"},
{"name":"Mesprit","type1":"Psychic","hp":"80","attack":"105","defense":"105"},
{"name":"Metagross","type1":"Steel","hp":"80","attack":"135","defense":"130"},
{"name":"Metang","type1":"Steel","hp":"60","attack":"75","defense":"100"},
{"name":"Metapod","type1":"Bug","hp":"50","attack":"20","defense":"55"},
{"name":"Mew","type1":"Psychic","hp":"100","attack":"100","defense":"100"},
{"name":"Mewtwo","type1":"Psychic","hp":"106","attack":"110","defense":"90"},
{"name":"Mienfoo","type1":"Fighting","hp":"45","attack":"85","defense":"50"},
{"name":"Mienshao","type1":"Fighting","hp":"65","attack":"125","defense":"60"},
{"name":"Mightyena","type1":"Dark","hp":"70","attack":"90","defense":"70"},
{"name":"Milcery","type1":"Fairy","hp":"45","attack":"40","defense":"40"},
{"name":"Milotic","type1":"Water","hp":"95","attack":"60","defense":"79"},
{"name":"Miltank","type1":"Normal","hp":"95","attack":"80","defense":"105"},
{"name":"Mime Jr.","type1":"Psychic","hp":"20","attack":"25","defense":"45"},
{"name":"Mimikyu","type1":"Ghost","hp":"55","attack":"90","defense":"80"},
{"name":"Minccino","type1":"Normal","hp":"55","attack":"50","defense":"40"},
{"name":"Minior Core Forme","type1":"Rock","hp":"60","attack":"100","defense":"60"},
{"name":"Minior Meteor Forme","type1":"Rock","hp":"60","attack":"60","defense":"100"},
{"name":"Minun","type1":"Electric","hp":"60","attack":"40","defense":"50"},
{"name":"Misdreavus","type1":"Ghost","hp":"60","attack":"60","defense":"60"},
{"name":"Mismagius","type1":"Ghost","hp":"60","attack":"60","defense":"60"},
{"name":"Moltres","type1":"Fire","hp":"90","attack":"100","defense":"90"},
{"name":"Monferno","type1":"Fire","hp":"64","attack":"78","defense":"52"},
{"name":"Morelull","type1":"Grass","hp":"40","attack":"35","defense":"55"},
{"name":"Morgrem","type1":"Dark","hp":"65","attack":"60","defense":"45"},
{"name":"Morpeko Full Belly Mode","type1":"Electric","hp":"58","attack":"95","defense":"58"},
{"name":"Morpeko Hangry Mode","type1":"Electric","hp":"58","attack":"95","defense":"58"},
{"name":"Mothim","type1":"Bug","hp":"70","attack":"94","defense":"50"},
{"name":"Mow Rotom","type1":"Electric","hp":"50","attack":"65","defense":"107"},
{"name":"Mr. Mime","type1":"Psychic","hp":"40","attack":"45","defense":"65"},
{"name":"Mr. Rime","type1":"Ice","hp":"80","attack":"85","defense":"75"},
{"name":"Mudbray","type1":"Ground","hp":"70","attack":"100","defense":"70"},
{"name":"Mudkip","type1":"Water","hp":"50","attack":"70","defense":"50"},
{"name":"Mudsdale","type1":"Ground","hp":"100","attack":"125","defense":"100"},
{"name":"Muk","type1":"Poison","hp":"105","attack":"105","defense":"75"},
{"name":"Munchlax","type1":"Normal","hp":"135","attack":"85","defense":"40"},
{"name":"Munna","type1":"Psychic","hp":"76","attack":"25","defense":"45"},
{"name":"Murkrow","type1":"Dark","hp":"60","attack":"85","defense":"42"},
{"name":"Musharna","type1":"Psychic","hp":"116","attack":"55","defense":"85"},
{"name":"Naganadel","type1":"Poison","hp":"73","attack":"73","defense":"73"},
{"name":"Natu","type1":"Psychic","hp":"40","attack":"50","defense":"45"},
{"name":"Necrozma","type1":"Psychic","hp":"97","attack":"107","defense":"101"},
{"name":"Nickit","type1":"Dark","hp":"40","attack":"28","defense":"28"},
{"name":"Nidoking","type1":"Poison","hp":"81","attack":"102","defense":"77"},
{"name":"Nidoqueen","type1":"Poison","hp":"90","attack":"92","defense":"87"},
{"name":"Nidoran♀","type1":"Poison","hp":"55","attack":"47","defense":"52"},
{"name":"Nidoran♂","type1":"Poison","hp":"46","attack":"57","defense":"40"},
{"name":"Nidorina","type1":"Poison","hp":"70","attack":"62","defense":"67"},
{"name":"Nidorino","type1":"Poison","hp":"61","attack":"72","defense":"57"},
{"name":"Nihilego","type1":"Rock","hp":"109","attack":"53","defense":"47"},
{"name":"Nincada","type1":"Bug","hp":"31","attack":"45","defense":"90"},
{"name":"Ninetales","type1":"Fire","hp":"73","attack":"76","defense":"75"},
{"name":"Ninjask","type1":"Bug","hp":"61","attack":"90","defense":"45"},
{"name":"Noctowl","type1":"Normal","hp":"100","attack":"50","defense":"50"},
{"name":"Noibat","type1":"Flying","hp":"40","attack":"30","defense":"35"},
{"name":"Noivern","type1":"Flying","hp":"85","attack":"70","defense":"80"},
{"name":"Nosepass","type1":"Rock","hp":"30","attack":"45","defense":"135"},
{"name":"Numel","type1":"Fire","hp":"60","attack":"60","defense":"40"},
{"name":"Nuzleaf","type1":"Grass","hp":"70","attack":"70","defense":"40"},
{"name":"Obstagoon","type1":"Dark","hp":"93","attack":"90","defense":"101"},
{"name":"Octillery","type1":"Water","hp":"75","attack":"105","defense":"75"},
{"name":"Oddish","type1":"Grass","hp":"45","attack":"50","defense":"55"},
{"name":"Omanyte","type1":"Rock","hp":"35","attack":"40","defense":"100"},
{"name":"Omastar","type1":"Rock","hp":"70","attack":"60","defense":"125"},
{"name":"Onix","type1":"Rock","hp":"35","attack":"45","defense":"160"},
{"name":"Oranguru","type1":"Normal","hp":"90","attack":"60","defense":"80"},
{"name":"Orbeetle","type1":"Bug","hp":"60","attack":"45","defense":"110"},
{"name":"Oricorio Baile Style","type1":"Fire","hp":"75","attack":"70","defense":"70"},
{"name":"Oricorio P'au Style","type1":"Psychic","hp":"75","attack":"70","defense":"70"},
{"name":"Oricorio Pom-Pom Style","type1":"Electric","hp":"75","attack":"70","defense":"70"},
{"name":"Oricorio Sensu Style","type1":"Ghost","hp":"75","attack":"70","defense":"70"},
{"name":"Oshawott","type1":"Water","hp":"55","attack":"55","defense":"45"},
{"name":"Pachirisu","type1":"Electric","hp":"60","attack":"45","defense":"70"},
{"name":"Palkia","type1":"Water","hp":"90","attack":"120","defense":"100"},
{"name":"Palossand","type1":"Ghost","hp":"85","attack":"75","defense":"110"},
{"name":"Palpitoad","type1":"Water","hp":"75","attack":"65","defense":"55"},
{"name":"Pancham","type1":"Fighting","hp":"67","attack":"82","defense":"62"},
{"name":"Pangoro","type1":"Fighting","hp":"95","attack":"124","defense":"78"},
{"name":"Panpour","type1":"Water","hp":"50","attack":"53","defense":"48"},
{"name":"Pansage","type1":"Grass","hp":"50","attack":"53","defense":"48"},
{"name":"Pansear","type1":"Fire","hp":"50","attack":"53","defense":"48"},
{"name":"Paras","type1":"Bug","hp":"35","attack":"70","defense":"55"},
{"name":"Parasect","type1":"Bug","hp":"60","attack":"95","defense":"80"},
{"name":"Passimian","type1":"Fighting","hp":"100","attack":"120","defense":"90"},
{"name":"Patrat","type1":"Normal","hp":"45","attack":"55","defense":"39"},
{"name":"Pawniard","type1":"Dark","hp":"45","attack":"85","defense":"70"},
{"name":"Pelipper","type1":"Water","hp":"60","attack":"50","defense":"100"},
{"name":"Perrserker","type1":"Steel","hp":"70","attack":"110","defense":"100"},
{"name":"Persian","type1":"Normal","hp":"65","attack":"70","defense":"60"},
{"name":"Petilil","type1":"Grass","hp":"45","attack":"35","defense":"50"},
{"name":"Phanpy","type1":"Ground","hp":"90","attack":"60","defense":"60"},
{"name":"Phantump","type1":"Ghost","hp":"43","attack":"70","defense":"48"},
{"name":"Pheromosa","type1":"Bug","hp":"71","attack":"137","defense":"37"},
{"name":"Phione","type1":"Water","hp":"80","attack":"80","defense":"80"},
{"name":"Pichu","type1":"Electric","hp":"20","attack":"40","defense":"15"},
{"name":"Pidgeot","type1":"Normal","hp":"83","attack":"80","defense":"75"},
{"name":"Pidgeotto","type1":"Normal","hp":"63","attack":"60","defense":"55"},
{"name":"Pidgey","type1":"Normal","hp":"40","attack":"45","defense":"40"},
{"name":"Pidove","type1":"Normal","hp":"50","attack":"55","defense":"50"},
{"name":"Pignite","type1":"Fire","hp":"90","attack":"93","defense":"55"},
{"name":"Pikachu","type1":"Electric","hp":"35","attack":"55","defense":"40"},
{"name":"Pikipek","type1":"Normal","hp":"35","attack":"75","defense":"30"},
{"name":"Piloswine","type1":"Ice","hp":"100","attack":"100","defense":"80"},
{"name":"Pincurchin","type1":"Electric","hp":"48","attack":"101","defense":"95"},
{"name":"Pineco","type1":"Bug","hp":"50","attack":"65","defense":"90"},
{"name":"Pinsir","type1":"Bug","hp":"65","attack":"125","defense":"100"},
{"name":"Piplup","type1":"Water","hp":"53","attack":"51","defense":"53"},
{"name":"Plusle","type1":"Electric","hp":"60","attack":"50","defense":"40"},
{"name":"Poipole","type1":"Poison","hp":"67","attack":"73","defense":"67"},
{"name":"Politoed","type1":"Water","hp":"90","attack":"75","defense":"75"},
{"name":"Poliwag","type1":"Water","hp":"40","attack":"50","defense":"40"},
{"name":"Poliwhirl","type1":"Water","hp":"65","attack":"65","defense":"65"},
{"name":"Poliwrath","type1":"Water","hp":"90","attack":"95","defense":"95"},
{"name":"Polteageist","type1":"Ghost","hp":"60","attack":"65","defense":"65"},
{"name":"Ponyta","type1":"Fire","hp":"50","attack":"85","defense":"55"},
{"name":"Poochyena","type1":"Dark","hp":"35","attack":"55","defense":"35"},
{"name":"Popplio","type1":"Water","hp":"50","attack":"54","defense":"54"},
{"name":"Porygon","type1":"Normal","hp":"65","attack":"60","defense":"70"},
{"name":"Porygon-Z","type1":"Normal","hp":"85","attack":"80","defense":"70"},
{"name":"Porygon2","type1":"Normal","hp":"85","attack":"80","defense":"90"},
{"name":"Primal Groudon","type1":"Ground","hp":"100","attack":"180","defense":"160"},
{"name":"Primal Kyogre","type1":"Water","hp":"100","attack":"150","defense":"90"},
{"name":"Primarina","type1":"Water","hp":"80","attack":"74","defense":"74"},
{"name":"Primeape","type1":"Fighting","hp":"65","attack":"105","defense":"60"},
{"name":"Prinplup","type1":"Water","hp":"64","attack":"66","defense":"68"},
{"name":"Probopass","type1":"Rock","hp":"60","attack":"55","defense":"145"},
{"name":"Psyduck","type1":"Water","hp":"50","attack":"52","defense":"48"},
{"name":"Pumpkaboo Average Size","type1":"Ghost","hp":"49","attack":"66","defense":"70"},
{"name":"Pumpkaboo Large Size","type1":"Ghost","hp":"54","attack":"66","defense":"70"},
{"name":"Pumpkaboo Small Size","type1":"Ghost","hp":"44","attack":"66","defense":"70"},
{"name":"Pumpkaboo Super Size","type1":"Ghost","hp":"59","attack":"66","defense":"70"},
{"name":"Pupitar","type1":"Rock","hp":"70","attack":"84","defense":"70"},
{"name":"Purrloin","type1":"Dark","hp":"41","attack":"50","defense":"37"},
{"name":"Purugly","type1":"Normal","hp":"71","attack":"82","defense":"64"},
{"name":"Pyroar","type1":"Fire","hp":"86","attack":"68","defense":"72"},
{"name":"Pyukumuku","type1":"Water","hp":"55","attack":"60","defense":"130"},
{"name":"Quagsire","type1":"Water","hp":"95","attack":"85","defense":"85"},
{"name":"Quilava","type1":"Fire","hp":"58","attack":"64","defense":"58"},
{"name":"Quilladin","type1":"Grass","hp":"61","attack":"78","defense":"95"},
{"name":"Qwilfish","type1":"Water","hp":"65","attack":"95","defense":"75"},
{"name":"Raboot","type1":"Fire","hp":"65","attack":"86","defense":"60"},
{"name":"Raichu","type1":"Electric","hp":"60","attack":"90","defense":"55"},
{"name":"Raikou","type1":"Electric","hp":"90","attack":"85","defense":"75"},
{"name":"Ralts","type1":"Psychic","hp":"28","attack":"25","defense":"25"},
{"name":"Rampardos","type1":"Rock","hp":"97","attack":"165","defense":"60"},
{"name":"Rapidash","type1":"Fire","hp":"65","attack":"100","defense":"70"},
{"name":"Raticate","type1":"Normal","hp":"55","attack":"81","defense":"60"},
{"name":"Rattata","type1":"Normal","hp":"30","attack":"56","defense":"35"},
{"name":"Rayquaza","type1":"Dragon","hp":"105","attack":"150","defense":"90"},
{"name":"Regice","type1":"Ice","hp":"80","attack":"50","defense":"100"},
{"name":"Regidrago","type1":"Dragon","hp":"200","attack":"100","defense":"50"},
{"name":"Regieleki","type1":"Electric","hp":"80","attack":"100","defense":"50"},
{"name":"Regigigas","type1":"Normal","hp":"110","attack":"160","defense":"110"},
{"name":"Regirock","type1":"Rock","hp":"80","attack":"100","defense":"200"},
{"name":"Registeel","type1":"Steel","hp":"80","attack":"75","defense":"150"},
{"name":"Relicanth","type1":"Water","hp":"100","attack":"90","defense":"130"},
{"name":"Remoraid","type1":"Water","hp":"35","attack":"65","defense":"35"},
{"name":"Reshiram","type1":"Dragon","hp":"100","attack":"120","defense":"100"},
{"name":"Reuniclus","type1":"Psychic","hp":"110","attack":"65","defense":"75"},
{"name":"Rhydon","type1":"Ground","hp":"105","attack":"130","defense":"120"},
{"name":"Rhyhorn","type1":"Ground","hp":"80","attack":"85","defense":"95"},
{"name":"Rhyperior","type1":"Ground","hp":"115","attack":"140","defense":"130"},
{"name":"Ribombee","type1":"Bug","hp":"60","attack":"55","defense":"60"},
{"name":"Rillaboom","type1":"Grass","hp":"100","attack":"125","defense":"90"},
{"name":"Riolu","type1":"Fighting","hp":"40","attack":"70","defense":"40"},
{"name":"Rockruff","type1":"Rock","hp":"45","attack":"65","defense":"40"},
{"name":"Roggenrola","type1":"Rock","hp":"55","attack":"75","defense":"85"},
{"name":"Rolycoly","type1":"Rock","hp":"30","attack":"40","defense":"50"},
{"name":"Rookidee","type1":"Flying","hp":"38","attack":"47","defense":"35"},
{"name":"Roselia","type1":"Grass","hp":"50","attack":"60","defense":"45"},
{"name":"Roserade","type1":"Grass","hp":"60","attack":"70","defense":"65"},
{"name":"Rotom","type1":"Electric","hp":"50","attack":"50","defense":"77"},
{"name":"Rowlet","type1":"Grass","hp":"68","attack":"55","defense":"55"},
{"name":"Rufflet","type1":"Normal","hp":"70","attack":"83","defense":"50"},
{"name":"Runerigus","type1":"Ground","hp":"58","attack":"95","defense":"145"},
{"name":"Sableye","type1":"Dark","hp":"50","attack":"75","defense":"75"},
{"name":"Salamence","type1":"Dragon","hp":"95","attack":"135","defense":"80"},
{"name":"Salandit","type1":"Poison","hp":"48","attack":"44","defense":"40"},
{"name":"Salazzle","type1":"Poison","hp":"68","attack":"64","defense":"60"},
{"name":"Samurott","type1":"Water","hp":"95","attack":"100","defense":"85"},
{"name":"Sandaconda","type1":"Ground","hp":"72","attack":"107","defense":"125"},
{"name":"Sandile","type1":"Ground","hp":"50","attack":"72","defense":"35"},
{"name":"Sandshrew","type1":"Ground","hp":"50","attack":"75","defense":"85"},
{"name":"Sandslash","type1":"Ground","hp":"75","attack":"100","defense":"110"},
{"name":"Sandygast","type1":"Ghost","hp":"55","attack":"55","defense":"80"},
{"name":"Sawk","type1":"Fighting","hp":"75","attack":"125","defense":"75"},
{"name":"Sawsbuck","type1":"Normal","hp":"80","attack":"100","defense":"70"},
{"name":"Scatterbug","type1":"Bug","hp":"38","attack":"35","defense":"40"},
{"name":"Sceptile","type1":"Grass","hp":"70","attack":"85","defense":"65"},
{"name":"Scizor","type1":"Bug","hp":"70","attack":"130","defense":"100"},
{"name":"Scolipede","type1":"Bug","hp":"60","attack":"100","defense":"89"},
{"name":"Scorbunny","type1":"Fire","hp":"50","attack":"71","defense":"40"},
{"name":"Scrafty","type1":"Dark","hp":"65","attack":"90","defense":"115"},
{"name":"Scraggy","type1":"Dark","hp":"50","attack":"75","defense":"70"},
{"name":"Scyther","type1":"Bug","hp":"70","attack":"110","defense":"80"},
{"name":"Seadra","type1":"Water","hp":"55","attack":"65","defense":"95"},
{"name":"Seaking","type1":"Water","hp":"80","attack":"92","defense":"65"},
{"name":"Sealeo","type1":"Ice","hp":"90","attack":"60","defense":"70"},
{"name":"Seedot","type1":"Grass","hp":"40","attack":"40","defense":"50"},
{"name":"Seel","type1":"Water","hp":"65","attack":"45","defense":"55"},
{"name":"Seismitoad","type1":"Water","hp":"105","attack":"95","defense":"75"},
{"name":"Sentret","type1":"Normal","hp":"35","attack":"46","defense":"34"},
{"name":"Serperior","type1":"Grass","hp":"75","attack":"75","defense":"95"},
{"name":"Servine","type1":"Grass","hp":"60","attack":"60","defense":"75"},
{"name":"Seviper","type1":"Poison","hp":"73","attack":"100","defense":"60"},
{"name":"Sewaddle","type1":"Bug","hp":"45","attack":"53","defense":"70"},
{"name":"Shadow Rider Calyrex","type1":"Psychic","hp":"100","attack":"85","defense":"80"},
{"name":"Sharpedo","type1":"Water","hp":"70","attack":"120","defense":"40"},
{"name":"Shaymin Land Forme","type1":"Grass","hp":"100","attack":"100","defense":"100"},
{"name":"Shaymin Sky Forme","type1":"Grass","hp":"100","attack":"103","defense":"75"},
{"name":"Shedinja","type1":"Bug","hp":"1","attack":"90","defense":"45"},
{"name":"Shelgon","type1":"Dragon","hp":"65","attack":"95","defense":"100"},
{"name":"Shellder","type1":"Water","hp":"30","attack":"65","defense":"100"},
{"name":"Shellos","type1":"Water","hp":"76","attack":"48","defense":"48"},
{"name":"Shelmet","type1":"Bug","hp":"50","attack":"40","defense":"85"},
{"name":"Shieldon","type1":"Rock","hp":"30","attack":"42","defense":"118"},
{"name":"Shiftry","type1":"Grass","hp":"90","attack":"100","defense":"60"},
{"name":"Shiinotic","type1":"Grass","hp":"60","attack":"45","defense":"80"},
{"name":"Shinx","type1":"Electric","hp":"45","attack":"65","defense":"34"},
{"name":"Shroomish","type1":"Grass","hp":"60","attack":"40","defense":"60"},
{"name":"Shuckle","type1":"Bug","hp":"20","attack":"10","defense":"230"},
{"name":"Shuppet","type1":"Ghost","hp":"44","attack":"75","defense":"35"},
{"name":"Sigilyph","type1":"Psychic","hp":"72","attack":"58","defense":"80"},
{"name":"Silcoon","type1":"Bug","hp":"50","attack":"35","defense":"55"},
{"name":"Silicobra","type1":"Ground","hp":"52","attack":"57","defense":"75"},
{"name":"Silvally","type1":"Normal","hp":"95","attack":"95","defense":"95"},
{"name":"Simipour","type1":"Water","hp":"75","attack":"98","defense":"63"},
{"name":"Simisage","type1":"Grass","hp":"75","attack":"98","defense":"63"},
{"name":"Simisear","type1":"Fire","hp":"75","attack":"98","defense":"63"},
{"name":"Sinistea","type1":"Ghost","hp":"40","attack":"45","defense":"45"},
{"name":"Sirfetch'd","type1":"Fighting","hp":"62","attack":"135","defense":"95"},
{"name":"Sizzlipede","type1":"Fire","hp":"50","attack":"65","defense":"45"},
{"name":"Skarmory","type1":"Steel","hp":"65","attack":"80","defense":"140"},
{"name":"Skiddo","type1":"Grass","hp":"66","attack":"65","defense":"48"},
{"name":"Skiploom","type1":"Grass","hp":"55","attack":"45","defense":"50"},
{"name":"Skitty","type1":"Normal","hp":"50","attack":"45","defense":"45"},
{"name":"Skorupi","type1":"Poison","hp":"40","attack":"50","defense":"90"},
{"name":"Skrelp","type1":"Poison","hp":"50","attack":"60","defense":"60"},
{"name":"Skuntank","type1":"Poison","hp":"103","attack":"93","defense":"67"},
{"name":"Skwovet","type1":"Normal","hp":"70","attack":"55","defense":"55"},
{"name":"Slaking","type1":"Normal","hp":"150","attack":"160","defense":"100"},
{"name":"Slakoth","type1":"Normal","hp":"60","attack":"60","defense":"60"},
{"name":"Sliggoo","type1":"Dragon","hp":"68","attack":"75","defense":"53"},
{"name":"Slowbro","type1":"Water","hp":"95","attack":"75","defense":"110"},
{"name":"Slowking","type1":"Water","hp":"95","attack":"75","defense":"80"},
{"name":"Slowpoke","type1":"Water","hp":"90","attack":"65","defense":"65"},
{"name":"Slugma","type1":"Fire","hp":"40","attack":"40","defense":"40"},
{"name":"Slurpuff","type1":"Fairy","hp":"82","attack":"80","defense":"86"},
{"name":"Smeargle","type1":"Normal","hp":"55","attack":"20","defense":"35"},
{"name":"Smoochum","type1":"Ice","hp":"45","attack":"30","defense":"15"},
{"name":"Sneasel","type1":"Dark","hp":"55","attack":"95","defense":"55"},
{"name":"Snivy","type1":"Grass","hp":"45","attack":"45","defense":"55"},
{"name":"Snom","type1":"Ice","hp":"30","attack":"25","defense":"35"},
{"name":"Snorlax","type1":"Normal","hp":"160","attack":"110","defense":"65"},
{"name":"Snorunt","type1":"Ice","hp":"50","attack":"50","defense":"50"},
{"name":"Snover","type1":"Grass","hp":"60","attack":"62","defense":"50"},
{"name":"Snubbull","type1":"Fairy","hp":"60","attack":"80","defense":"50"},
{"name":"Sobble","type1":"Water","hp":"50","attack":"40","defense":"40"},
{"name":"Solgaleo","type1":"Psychic","hp":"137","attack":"137","defense":"107"},
{"name":"Solosis","type1":"Psychic","hp":"45","attack":"30","defense":"40"},
{"name":"Solrock","type1":"Rock","hp":"70","attack":"95","defense":"85"},
{"name":"Spearow","type1":"Normal","hp":"40","attack":"60","defense":"30"},
{"name":"Spectrier","type1":"Ghost","hp":"100","attack":"65","defense":"60"},
{"name":"Spewpa","type1":"Bug","hp":"45","attack":"22","defense":"60"},
{"name":"Spheal","type1":"Ice","hp":"70","attack":"40","defense":"50"},
{"name":"Spinarak","type1":"Bug","hp":"40","attack":"60","defense":"40"},
{"name":"Spinda","type1":"Normal","hp":"60","attack":"60","defense":"60"},
{"name":"Spiritomb","type1":"Ghost","hp":"50","attack":"92","defense":"108"},
{"name":"Spoink","type1":"Psychic","hp":"60","attack":"25","defense":"35"},
{"name":"Spritzee","type1":"Fairy","hp":"78","attack":"52","defense":"60"},
{"name":"Squirtle","type1":"Water","hp":"44","attack":"48","defense":"65"},
{"name":"Stakataka","type1":"Rock","hp":"61","attack":"131","defense":"211"},
{"name":"Stantler","type1":"Normal","hp":"73","attack":"95","defense":"62"},
{"name":"Staraptor","type1":"Normal","hp":"85","attack":"120","defense":"70"},
{"name":"Staravia","type1":"Normal","hp":"55","attack":"75","defense":"50"},
{"name":"Starly","type1":"Normal","hp":"40","attack":"55","defense":"30"},
{"name":"Starmie","type1":"Water","hp":"60","attack":"75","defense":"85"},
{"name":"Staryu","type1":"Water","hp":"30","attack":"45","defense":"55"},
{"name":"Steelix","type1":"Steel","hp":"75","attack":"85","defense":"200"},
{"name":"Steenee","type1":"Grass","hp":"52","attack":"40","defense":"48"},
{"name":"Stonjourner","type1":"Rock","hp":"100","attack":"125","defense":"135"},
{"name":"Stoutland","type1":"Normal","hp":"85","attack":"110","defense":"90"},
{"name":"Stufful","type1":"Normal","hp":"70","attack":"75","defense":"50"},
{"name":"Stunfisk","type1":"Ground","hp":"109","attack":"66","defense":"84"},
{"name":"Stunky","type1":"Poison","hp":"63","attack":"63","defense":"47"},
{"name":"Sudowoodo","type1":"Rock","hp":"70","attack":"100","defense":"115"},
{"name":"Suicune","type1":"Water","hp":"100","attack":"75","defense":"115"},
{"name":"Sunflora","type1":"Grass","hp":"75","attack":"75","defense":"55"},
{"name":"Sunkern","type1":"Grass","hp":"30","attack":"30","defense":"30"},
{"name":"Surskit","type1":"Bug","hp":"40","attack":"30","defense":"32"},
{"name":"Swablu","type1":"Normal","hp":"45","attack":"40","defense":"60"},
{"name":"Swadloon","type1":"Bug","hp":"55","attack":"63","defense":"90"},
{"name":"Swalot","type1":"Poison","hp":"100","attack":"73","defense":"83"},
{"name":"Swampert","type1":"Water","hp":"100","attack":"110","defense":"90"},
{"name":"Swanna","type1":"Water","hp":"75","attack":"87","defense":"63"},
{"name":"Swellow","type1":"Normal","hp":"60","attack":"85","defense":"60"},
{"name":"Swinub","type1":"Ice","hp":"50","attack":"50","defense":"40"},
{"name":"Swirlix","type1":"Fairy","hp":"62","attack":"48","defense":"66"},
{"name":"Swoobat","type1":"Psychic","hp":"67","attack":"57","defense":"55"},
{"name":"Sylveon","type1":"Fairy","hp":"95","attack":"65","defense":"65"},
{"name":"Taillow","type1":"Normal","hp":"40","attack":"55","defense":"30"},
{"name":"Talonflame","type1":"Fire","hp":"78","attack":"81","defense":"71"},
{"name":"Tangela","type1":"Grass","hp":"65","attack":"55","defense":"115"},
{"name":"Tangrowth","type1":"Grass","hp":"100","attack":"100","defense":"125"},
{"name":"Tapu Bulu","type1":"Grass","hp":"70","attack":"130","defense":"115"},
{"name":"Tapu Fini","type1":"Water","hp":"70","attack":"75","defense":"115"},
{"name":"Tapu Koko","type1":"Electric","hp":"70","attack":"115","defense":"85"},
{"name":"Tapu Lele","type1":"Psychic","hp":"70","attack":"85","defense":"75"},
{"name":"Tauros","type1":"Normal","hp":"75","attack":"100","defense":"95"},
{"name":"Teddiursa","type1":"Normal","hp":"60","attack":"80","defense":"50"},
{"name":"Tentacool","type1":"Water","hp":"40","attack":"40","defense":"35"},
{"name":"Tentacruel","type1":"Water","hp":"80","attack":"70","defense":"65"},
{"name":"Tepig","type1":"Fire","hp":"65","attack":"63","defense":"45"},
{"name":"Terrakion","type1":"Rock","hp":"91","attack":"129","defense":"90"},
{"name":"Thievul","type1":"Dark","hp":"70","attack":"58","defense":"58"},
{"name":"Throh","type1":"Fighting","hp":"120","attack":"100","defense":"85"},
{"name":"Thundurus Incarnate Forme","type1":"Electric","hp":"79","attack":"115","defense":"70"},
{"name":"Thundurus Therian Forme","type1":"Electric","hp":"79","attack":"105","defense":"70"},
{"name":"Thwackey","type1":"Grass","hp":"70","attack":"85","defense":"70"},
{"name":"Timburr","type1":"Fighting","hp":"75","attack":"80","defense":"55"},
{"name":"Tirtouga","type1":"Water","hp":"54","attack":"78","defense":"103"},
{"name":"Togedemaru","type1":"Electric","hp":"65","attack":"98","defense":"63"},
{"name":"Togekiss","type1":"Fairy","hp":"85","attack":"50","defense":"95"},
{"name":"Togepi","type1":"Fairy","hp":"35","attack":"20","defense":"65"},
{"name":"Togetic","type1":"Fairy","hp":"55","attack":"40","defense":"85"},
{"name":"Torchic","type1":"Fire","hp":"45","attack":"60","defense":"40"},
{"name":"Torkoal","type1":"Fire","hp":"70","attack":"85","defense":"140"},
{"name":"Tornadus Incarnate Forme","type1":"Flying","hp":"79","attack":"115","defense":"70"},
{"name":"Tornadus Therian Forme","type1":"Flying","hp":"79","attack":"100","defense":"80"},
{"name":"Torracat","type1":"Fire","hp":"65","attack":"85","defense":"50"},
{"name":"Torterra","type1":"Grass","hp":"95","attack":"109","defense":"105"},
{"name":"Totodile","type1":"Water","hp":"50","attack":"65","defense":"64"},
{"name":"Toucannon","type1":"Normal","hp":"80","attack":"120","defense":"75"},
{"name":"Toxapex","type1":"Poison","hp":"50","attack":"63","defense":"152"},
{"name":"Toxel","type1":"Electric","hp":"40","attack":"38","defense":"35"},
{"name":"Toxicroak","type1":"Poison","hp":"83","attack":"106","defense":"65"},
{"name":"Toxitricity Low Key Forme","type1":"Electric","hp":"75","attack":"98","defense":"70"},
{"name":"Toxtricity Amped Forme","type1":"Electric","hp":"75","attack":"98","defense":"70"},
{"name":"Tranquill","type1":"Normal","hp":"62","attack":"77","defense":"62"},
{"name":"Trapinch","type1":"Ground","hp":"45","attack":"100","defense":"45"},
{"name":"Treecko","type1":"Grass","hp":"40","attack":"45","defense":"35"},
{"name":"Trevenant","type1":"Ghost","hp":"85","attack":"110","defense":"76"},
{"name":"Tropius","type1":"Grass","hp":"99","attack":"68","defense":"83"},
{"name":"Trubbish","type1":"Poison","hp":"50","attack":"50","defense":"62"},
{"name":"Trumbeak","type1":"Normal","hp":"55","attack":"85","defense":"50"},
{"name":"Tsareena","type1":"Grass","hp":"72","attack":"120","defense":"98"},
{"name":"Turtonator","type1":"Fire","hp":"60","attack":"78","defense":"135"},
{"name":"Turtwig","type1":"Grass","hp":"55","attack":"68","defense":"64"},
{"name":"Tympole","type1":"Water","hp":"50","attack":"50","defense":"40"},
{"name":"Tynamo","type1":"Electric","hp":"35","attack":"55","defense":"40"},
{"name":"Type: Null","type1":"Normal","hp":"95","attack":"95","defense":"95"},
{"name":"Typhlosion","type1":"Fire","hp":"78","attack":"84","defense":"78"},
{"name":"Tyranitar","type1":"Rock","hp":"100","attack":"134","defense":"110"},
{"name":"Tyrantrum","type1":"Rock","hp":"82","attack":"121","defense":"119"},
{"name":"Tyrogue","type1":"Fighting","hp":"35","attack":"35","defense":"35"},
{"name":"Tyrunt","type1":"Rock","hp":"58","attack":"89","defense":"77"},
{"name":"Ultra Necrozma","type1":"Psychic","hp":"97","attack":"167","defense":"97"},
{"name":"Umbreon","type1":"Dark","hp":"95","attack":"65","defense":"110"},
{"name":"Unfezant","type1":"Normal","hp":"80","attack":"115","defense":"80"},
{"name":"Unown","type1":"Psychic","hp":"48","attack":"72","defense":"48"},
{"name":"Ursaring","type1":"Normal","hp":"90","attack":"130","defense":"75"},
{"name":"Urshifu Rapid Strike Style","type1":"Fighting","hp":"100","attack":"130","defense":"100"},
{"name":"Urshifu Single Strike Style","type1":"Fighting","hp":"100","attack":"130","defense":"100"},
{"name":"Uxie","type1":"Psychic","hp":"75","attack":"75","defense":"130"},
{"name":"Vanillish","type1":"Ice","hp":"51","attack":"65","defense":"65"},
{"name":"Vanillite","type1":"Ice","hp":"36","attack":"50","defense":"50"},
{"name":"Vanilluxe","type1":"Ice","hp":"71","attack":"95","defense":"85"},
{"name":"Vaporeon","type1":"Water","hp":"130","attack":"65","defense":"60"},
{"name":"Venipede","type1":"Bug","hp":"30","attack":"45","defense":"59"},
{"name":"Venomoth","type1":"Bug","hp":"70","attack":"65","defense":"60"},
{"name":"Venonat","type1":"Bug","hp":"60","attack":"55","defense":"50"},
{"name":"Venusaur","type1":"Grass","hp":"80","attack":"82","defense":"83"},
{"name":"Vespiquen","type1":"Bug","hp":"70","attack":"80","defense":"102"},
{"name":"Vibrava","type1":"Ground","hp":"50","attack":"70","defense":"50"},
{"name":"Victini","type1":"Psychic","hp":"100","attack":"100","defense":"100"},
{"name":"Victreebel","type1":"Grass","hp":"80","attack":"105","defense":"65"},
{"name":"Vigoroth","type1":"Normal","hp":"80","attack":"80","defense":"80"},
{"name":"Vikavolt","type1":"Bug","hp":"77","attack":"70","defense":"90"},
{"name":"Vileplume","type1":"Grass","hp":"75","attack":"80","defense":"85"},
{"name":"Virizion","type1":"Grass","hp":"91","attack":"90","defense":"72"},
{"name":"Vivillon","type1":"Bug","hp":"80","attack":"52","defense":"50"},
{"name":"Volbeat","type1":"Bug","hp":"65","attack":"73","defense":"55"},
{"name":"Volcanion","type1":"Fire","hp":"80","attack":"110","defense":"120"},
{"name":"Volcarona","type1":"Bug","hp":"85","attack":"60","defense":"65"},
{"name":"Voltorb","type1":"Electric","hp":"40","attack":"30","defense":"50"},
{"name":"Vullaby","type1":"Dark","hp":"70","attack":"55","defense":"75"},
{"name":"Vulpix","type1":"Fire","hp":"38","attack":"41","defense":"40"},
{"name":"Wailmer","type1":"Water","hp":"130","attack":"70","defense":"35"},
{"name":"Wailord","type1":"Water","hp":"170","attack":"90","defense":"45"},
{"name":"Walrein","type1":"Ice","hp":"110","attack":"80","defense":"90"},
{"name":"Wartortle","type1":"Water","hp":"59","attack":"63","defense":"80"},
{"name":"Wash Rotom","type1":"Electric","hp":"50","attack":"65","defense":"107"},
{"name":"Watchog","type1":"Normal","hp":"60","attack":"85","defense":"69"},
{"name":"Weavile","type1":"Dark","hp":"70","attack":"120","defense":"65"},
{"name":"Weedle","type1":"Bug","hp":"40","attack":"35","defense":"30"},
{"name":"Weepinbell","type1":"Grass","hp":"65","attack":"90","defense":"50"},
{"name":"Weezing","type1":"Poison","hp":"65","attack":"90","defense":"120"},
{"name":"Whimsicott","type1":"Grass","hp":"60","attack":"67","defense":"85"},
{"name":"Whirlipede","type1":"Bug","hp":"40","attack":"55","defense":"99"},
{"name":"Whiscash","type1":"Water","hp":"110","attack":"78","defense":"73"},
{"name":"Whismur","type1":"Normal","hp":"64","attack":"51","defense":"23"},
{"name":"White Kyurem","type1":"Dragon","hp":"125","attack":"120","defense":"90"},
{"name":"Wigglytuff","type1":"Normal","hp":"140","attack":"70","defense":"45"},
{"name":"Wimpod","type1":"Bug","hp":"25","attack":"35","defense":"40"},
{"name":"Wingull","type1":"Water","hp":"40","attack":"30","defense":"30"},
{"name":"Wishiwashi School Forme","type1":"Water","hp":"45","attack":"140","defense":"130"},
{"name":"Wishiwashi Solo Forme","type1":"Water","hp":"45","attack":"20","defense":"20"},
{"name":"Wobbuffet","type1":"Psychic","hp":"190","attack":"33","defense":"58"},
{"name":"Woobat","type1":"Psychic","hp":"55","attack":"45","defense":"43"},
{"name":"Wooloo","type1":"Normal","hp":"42","attack":"40","defense":"55"},
{"name":"Wooper","type1":"Water","hp":"55","attack":"45","defense":"45"},
{"name":"Wormadam Plant Cloak","type1":"Bug","hp":"60","attack":"59","defense":"85"},
{"name":"Wormadam Sandy Cloak","type1":"Bug","hp":"60","attack":"79","defense":"105"},
{"name":"Wormadam Trash Cloak","type1":"Bug","hp":"60","attack":"69","defense":"95"},
{"name":"Wurmple","type1":"Bug","hp":"45","attack":"45","defense":"35"},
{"name":"Wynaut","type1":"Psychic","hp":"95","attack":"23","defense":"48"},
{"name":"Xatu","type1":"Psychic","hp":"65","attack":"75","defense":"70"},
{"name":"Xerneas","type1":"Fairy","hp":"126","attack":"131","defense":"95"},
{"name":"Xurkitree","type1":"Electric","hp":"83","attack":"89","defense":"71"},
{"name":"Yamask","type1":"Ghost","hp":"38","attack":"30","defense":"85"},
{"name":"Yamper","type1":"Electric","hp":"59","attack":"45","defense":"50"},
{"name":"Yanma","type1":"Bug","hp":"65","attack":"65","defense":"45"},
{"name":"Yanmega","type1":"Bug","hp":"86","attack":"76","defense":"86"},
{"name":"Yungoos","type1":"Normal","hp":"48","attack":"70","defense":"30"},
{"name":"Yveltal","type1":"Dark","hp":"126","attack":"131","defense":"95"},
{"name":"Zacian Crowned Sword Forme","type1":"Fairy","hp":"92","attack":"170","defense":"115"},
{"name":"Zacian Hero of Many Battles","type1":"Fairy","hp":"92","attack":"130","defense":"115"},
{"name":"Zamazenta Crowned Sheild Forme","type1":"Fighting","hp":"92","attack":"130","defense":"145"},
{"name":"Zamazenta Hero of Many Battles","type1":"Fighting","hp":"92","attack":"130","defense":"115"},
{"name":"Zangoose","type1":"Normal","hp":"73","attack":"115","defense":"60"},
{"name":"Zapdos","type1":"Electric","hp":"90","attack":"90","defense":"85"},
{"name":"Zarude","type1":"Dark","hp":"105","attack":"120","defense":"105"},
{"name":"Zebstrika","type1":"Electric","hp":"75","attack":"100","defense":"63"},
{"name":"Zekrom","type1":"Dragon","hp":"100","attack":"150","defense":"120"},
{"name":"Zeraora","type1":"Electric","hp":"88","attack":"112","defense":"75"},
{"name":"Zigzagoon","type1":"Normal","hp":"38","attack":"30","defense":"41"},
{"name":"Zoroark","type1":"Dark","hp":"60","attack":"105","defense":"60"},
{"name":"Zorua","type1":"Dark","hp":"40","attack":"65","defense":"40"},
{"name":"Zubat","type1":"Poison","hp":"40","attack":"45","defense":"35"},
{"name":"Zweilous","type1":"Dark","hp":"72","attack":"85","defense":"70"},
{"name":"Zygarde 10% Forme","type1":"Dragon","hp":"54","attack":"100","defense":"71"},
{"name":"Zygarde 50% Forme","type1":"Dragon","hp":"108","attack":"100","defense":"121"},
{"name":"Zygarde Complete Forme","type1":"Dragon","hp":"216","attack":"100","defense":"121"},
{"name":"name","type1":"type1","hp":"hp","attack":"attack","defense":"defense"}]
